{"cod":"200","message":0,"cnt":40,"list":[{"dt":1778932800,"main":{"temp":42.29,"feels_like":39.28,"temp_min":42.29,"temp_max":42.29,"pressure":998,"sea_level":998,"grnd_level":974,"humidity":10,"temp_kf":0},"weather":[{"id":800,"main":"Clear","description":"clear sky","icon":"01d"}],"clouds":{"all":6},"wind":{"speed":5.17,"deg":302,"gust":7.23},"visibility":10000,"pop":0,"sys":{"pod":"d"},"dt_txt":"2026-05-16 12:00:00"},{"dt":1778943600,"main":{"temp":41.49,"feels_like":38.71,"temp_min":39.89,"temp_max":41.49,"pressure":998,"sea_level":998,"grnd_level":975,"humidity":11,"temp_kf":1.6},"weather":[{"id":800,"main":"Clear","description":"clear sky","icon":"01n"}],"clouds":{"all":10},"wind":{"speed":3.43,"deg":291,"gust":7.47},"visibility":10000,"pop":0,"sys":{"pod":"n"},"dt_txt":"2026-05-16 15:00:00"},{"dt":1778954400,"main":{"temp":39.92,"feels_like":37.27,"temp_min":38.73,"temp_max":39.92,"pressure":999,"sea_level":999,"grnd_level":976,"humidity":12,"temp_kf":1.19},"weather":[{"id":801,"main":"Clouds","description":"few clouds","icon":"02n"}],"clouds":{"all":23},"wind":{"speed":4.38,"deg":290,"gust":9.94},"visibility":10000,"pop":0,"sys":{"pod":"n"},"dt_txt":"2026-05-16 18:00:00"},{"dt":1778965200,"main":{"temp":35.97,"feels_like":33.65,"temp_min":35.97,"temp_max":35.97,"pressure":999,"sea_level":999,"grnd_level":975,"humidity":16,"temp_kf":0},"weather":[{"id":802,"main":"Clouds","description":"scattered clouds","icon":"03n"}],"clouds":{"all":41},"wind":{"speed":3.08,"deg":301,"gust":6.96},"visibility":10000,"pop":0,"sys":{"pod":"n"},"dt_txt":"2026-05-16 21:00:00"},{"dt":1778976000,"main":{"temp":34.35,"feels_like":32.15,"temp_min":34.35,"temp_max":34.35,"pressure":1000,"sea_level":1000,"grnd_level":976,"humidity":18,"temp_kf":0},"weather":[{"id":801,"main":"Clouds","description":"few clouds","icon":"02d"}],"clouds":{"all":21},"wind":{"speed":2.72,"deg":295,"gust":4.94},"visibility":10000,"pop":0,"sys":{"pod":"d"},"dt_txt":"2026-05-17 00:00:00"},{"dt":1778986800,"main":{"temp":38.72,"feels_like":36.18,"temp_min":38.72,"temp_max":38.72,"pressure":1002,"sea_level":1002,"grnd_level":978,"humidity":13,"temp_kf":0},"weather":[{"id":800,"main":"Clear","description":"clear sky","icon":"01d"}],"clouds":{"all":0},"wind":{"speed":3.11,"deg":311,"gust":5.31},"visibility":10000,"pop":0,"sys":{"pod":"d"},"dt_txt":"2026-05-17 03:00:00"},{"dt":1778997600,"main":{"temp":43.22,"feels_like":40.24,"temp_min":43.22,"temp_max":43.22,"pressure":1001,"sea_level":1001,"grnd_level":977,"humidity":10,"temp_kf":0},"weather":[{"id":800,"main":"Clear","description":"clear sky","icon":"01d"}],"clouds":{"all":0},"wind":{"speed":5.57,"deg":289,"gust":9.31},"visibility":10000,"pop":0,"sys":{"pod":"d"},"dt_txt":"2026-05-17 06:00:00"},{"dt":1779008400,"main":{"temp":45.38,"feels_like":42.1,"temp_min":45.38,"temp_max":45.38,"pressure":997,"sea_level":997,"grnd_level":974,"humidity":9,"temp_kf":0},"weather":[{"id":800,"main":"Clear","description":"clear sky","icon":"01d"}],"clouds":{"all":1},"wind":{"speed":6.54,"deg":304,"gust":8.83},"visibility":10000,"pop":0,"sys":{"pod":"d"},"dt_txt":"2026-05-17 09:00:00"},{"dt":1779019200,"main":{"temp":44.87,"feels_like":41.58,"temp_min":44.87,"temp_max":44.87,"pressure":996,"sea_level":996,"grnd_level":972,"humidity":9,"temp_kf":0},"weather":[{"id":800,"main":"Clear","description":"clear sky","icon":"01d"}],"clouds":{"all":4},"wind":{"speed":7.4,"deg":282,"gust":8.83},"visibility":10000,"pop":0,"sys":{"pod":"d"},"dt_txt":"2026-05-17 12:00:00"},{"dt":1779030000,"main":{"temp":41.79,"feels_like":39.03,"temp_min":41.79,"temp_max":41.79,"pressure":997,"sea_level":997,"grnd_level":973,"humidity":11,"temp_kf":0},"weather":[{"id":802,"main":"Clouds","description":"scattered clouds","icon":"03n"}],"clouds":{"all":32},"wind":{"speed":4.69,"deg":267,"gust":9.08},"visibility":10000,"pop":0,"sys":{"pod":"n"},"dt_txt":"2026-05-17 15:00:00"},{"dt":1779040800,"main":{"temp":40.25,"feels_like":37.62,"temp_min":40.25,"temp_max":40.25,"pressure":997,"sea_level":997,"grnd_level":973,"humidity":12,"temp_kf":0},"weather":[{"id":801,"main":"Clouds","description":"few clouds","icon":"02n"}],"clouds":{"all":17},"wind":{"speed":5.41,"deg":282,"gust":11.9},"visibility":10000,"pop":0,"sys":{"pod":"n"},"dt_txt":"2026-05-17 18:00:00"},{"dt":1779051600,"main":{"temp":37.29,"feels_like":34.81,"temp_min":37.29,"temp_max":37.29,"pressure":996,"sea_level":996,"grnd_level":972,"humidity":14,"temp_kf":0},"weather":[{"id":800,"main":"Clear","description":"clear sky","icon":"01n"}],"clouds":{"all":0},"wind":{"speed":3.72,"deg":298,"gust":8.38},"visibility":10000,"pop":0,"sys":{"pod":"n"},"dt_txt":"2026-05-17 21:00:00"},{"dt":1779062400,"main":{"temp":35.33,"feels_like":32.9,"temp_min":35.33,"temp_max":35.33,"pressure":997,"sea_level":997,"grnd_level":973,"humidity":15,"temp_kf":0},"weather":[{"id":800,"main":"Clear","description":"clear sky","icon":"01d"}],"clouds":{"all":0},"wind":{"speed":2.86,"deg":284,"gust":6.14},"visibility":10000,"pop":0,"sys":{"pod":"d"},"dt_txt":"2026-05-18 00:00:00"},{"dt":1779073200,"main":{"temp":38.93,"feels_like":36.24,"temp_min":38.93,"temp_max":38.93,"pressure":999,"sea_level":999,"grnd_level":975,"humidity":12,"temp_kf":0},"weather":[{"id":800,"main":"Clear","description":"clear sky","icon":"01d"}],"clouds":{"all":0},"wind":{"speed":4.69,"deg":281,"gust":7.12},"visibility":10000,"pop":0,"sys":{"pod":"d"},"dt_txt":"2026-05-18 03:00:00"},{"dt":1779084000,"main":{"temp":43.88,"feels_like":40.58,"temp_min":43.88,"temp_max":43.88,"pressure":999,"sea_level":999,"grnd_level":975,"humidity":9,"temp_kf":0},"weather":[{"id":800,"main":"Clear","description":"clear sky","icon":"01d"}],"clouds":{"all":0},"wind":{"speed":5.51,"deg":280,"gust":10.34},"visibility":10000,"pop":0,"sys":{"pod":"d"},"dt_txt":"2026-05-18 06:00:00"},{"dt":1779094800,"main":{"temp":46.79,"feels_like":42.55,"temp_min":46.79,"temp_max":46.79,"pressure":996,"sea_level":996,"grnd_level":972,"humidity":7,"temp_kf":0},"weather":[{"id":800,"main":"Clear","description":"clear sky","icon":"01d"}],"clouds":{"all":0},"wind":{"speed":6.79,"deg":298,"gust":9.12},"visibility":10000,"pop":0,"sys":{"pod":"d"},"dt_txt":"2026-05-18 09:00:00"},{"dt":1779105600,"main":{"temp":46.49,"feels_like":42.28,"temp_min":46.49,"temp_max":46.49,"pressure":995,"sea_level":995,"grnd_level":971,"humidity":7,"temp_kf":0},"weather":[{"id":800,"main":"Clear","description":"clear sky","icon":"01d"}],"clouds":{"all":0},"wind":{"speed":7.27,"deg":283,"gust":9.28},"visibility":10000,"pop":0,"sys":{"pod":"d"},"dt_txt":"2026-05-18 12:00:00"},{"dt":1779116400,"main":{"temp":43.75,"feels_like":40.13,"temp_min":43.75,"temp_max":43.75,"pressure":996,"sea_level":996,"grnd_level":972,"humidity":8,"temp_kf":0},"weather":[{"id":800,"main":"Clear","description":"clear sky","icon":"01n"}],"clouds":{"all":0},"wind":{"speed":6.45,"deg":271,"gust":11.37},"visibility":10000,"pop":0,"sys":{"pod":"n"},"dt_txt":"2026-05-18 15:00:00"},{"dt":1779127200,"main":{"temp":41.09,"feels_like":38.07,"temp_min":41.09,"temp_max":41.09,"pressure":996,"sea_level":996,"grnd_level":973,"humidity":10,"temp_kf":0},"weather":[{"id":800,"main":"Clear","description":"clear sky","icon":"01n"}],"clouds":{"all":0},"wind":{"speed":6.58,"deg":269,"gust":13.51},"visibility":10000,"pop":0,"sys":{"pod":"n"},"dt_txt":"2026-05-18 18:00:00"},{"dt":1779138000,"main":{"temp":38.87,"feels_like":36.18,"temp_min":38.87,"temp_max":38.87,"pressure":996,"sea_level":996,"grnd_level":973,"humidity":12,"temp_kf":0},"weather":[{"id":800,"main":"Clear","description":"clear sky","icon":"01n"}],"clouds":{"all":0},"wind":{"speed":7.2,"deg":276,"gust":14.82},"visibility":10000,"pop":0,"sys":{"pod":"n"},"dt_txt":"2026-05-18 21:00:00"},{"dt":1779148800,"main":{"temp":37.2,"feels_like":34.32,"temp_min":37.2,"temp_max":37.2,"pressure":998,"sea_level":998,"grnd_level":974,"humidity":10,"temp_kf":0},"weather":[{"id":800,"main":"Clear","description":"clear sky","icon":"01d"}],"clouds":{"all":4},"wind":{"speed":6.51,"deg":286,"gust":14.84},"visibility":10000,"pop":0,"sys":{"pod":"d"},"dt_txt":"2026-05-19 00:00:00"},{"dt":1779159600,"main":{"temp":39.3,"feels_like":36.17,"temp_min":39.3,"temp_max":39.3,"pressure":1000,"sea_level":1000,"grnd_level":976,"humidity":9,"temp_kf":0},"weather":[{"id":800,"main":"Clear","description":"clear sky","icon":"01d"}],"clouds":{"all":2},"wind":{"speed":7.56,"deg":297,"gust":12.41},"visibility":10000,"pop":0,"sys":{"pod":"d"},"dt_txt":"2026-05-19 03:00:00"},{"dt":1779170400,"main":{"temp":43.75,"feels_like":40.45,"temp_min":43.75,"temp_max":43.75,"pressure":1000,"sea_level":1000,"grnd_level":976,"humidity":9,"temp_kf":0},"weather":[{"id":800,"main":"Clear","description":"clear sky","icon":"01d"}],"clouds":{"all":1},"wind":{"speed":7.27,"deg":290,"gust":8.98},"visibility":10000,"pop":0,"sys":{"pod":"d"},"dt_txt":"2026-05-19 06:00:00"},{"dt":1779181200,"main":{"temp":46.08,"feels_like":42.35,"temp_min":46.08,"temp_max":46.08,"pressure":997,"sea_level":997,"grnd_level":974,"humidity":8,"temp_kf":0},"weather":[{"id":800,"main":"Clear","description":"clear sky","icon":"01d"}],"clouds":{"all":0},"wind":{"speed":6.32,"deg":283,"gust":6.53},"visibility":10000,"pop":0,"sys":{"pod":"d"},"dt_txt":"2026-05-19 09:00:00"},{"dt":1779192000,"main":{"temp":45.23,"feels_like":41.14,"temp_min":45.23,"temp_max":45.23,"pressure":996,"sea_level":996,"grnd_level":972,"humidity":7,"temp_kf":0},"weather":[{"id":800,"main":"Clear","description":"clear sky","icon":"01d"}],"clouds":{"all":0},"wind":{"speed":6.57,"deg":283,"gust":7.32},"visibility":10000,"pop":0,"sys":{"pod":"d"},"dt_txt":"2026-05-19 12:00:00"},{"dt":1779202800,"main":{"temp":41.79,"feels_like":38.53,"temp_min":41.79,"temp_max":41.79,"pressure":997,"sea_level":997,"grnd_level":973,"humidity":9,"temp_kf":0},"weather":[{"id":800,"main":"Clear","description":"clear sky","icon":"01n"}],"clouds":{"all":0},"wind":{"speed":4.72,"deg":306,"gust":8.92},"visibility":10000,"pop":0,"sys":{"pod":"n"},"dt_txt":"2026-05-19 15:00:00"},{"dt":1779213600,"main":{"temp":39.7,"feels_like":37.04,"temp_min":39.7,"temp_max":39.7,"pressure":998,"sea_level":998,"grnd_level":974,"humidity":12,"temp_kf":0},"weather":[{"id":800,"main":"Clear","description":"clear sky","icon":"01n"}],"clouds":{"all":0},"wind":{"speed":6.3,"deg":271,"gust":12.08},"visibility":10000,"pop":0,"sys":{"pod":"n"},"dt_txt":"2026-05-19 18:00:00"},{"dt":1779224400,"main":{"temp":38.22,"feels_like":35.65,"temp_min":38.22,"temp_max":38.22,"pressure":996,"sea_level":996,"grnd_level":972,"humidity":13,"temp_kf":0},"weather":[{"id":800,"main":"Clear","description":"clear sky","icon":"01n"}],"clouds":{"all":0},"wind":{"speed":6.08,"deg":268,"gust":12.99},"visibility":10000,"pop":0,"sys":{"pod":"n"},"dt_txt":"2026-05-19 21:00:00"},{"dt":1779235200,"main":{"temp":34.68,"feels_like":32.69,"temp_min":34.68,"temp_max":34.68,"pressure":998,"sea_level":998,"grnd_level":974,"humidity":20,"temp_kf":0},"weather":[{"id":800,"main":"Clear","description":"clear sky","icon":"01d"}],"clouds":{"all":0},"wind":{"speed":2.97,"deg":313,"gust":7.61},"visibility":10000,"pop":0,"sys":{"pod":"d"},"dt_txt":"2026-05-20 00:00:00"},{"dt":1779246000,"main":{"temp":36.92,"feels_like":36.81,"temp_min":36.92,"temp_max":36.92,"pressure":1001,"sea_level":1001,"grnd_level":976,"humidity":27,"temp_kf":0},"weather":[{"id":800,"main":"Clear","description":"clear sky","icon":"01d"}],"clouds":{"all":2},"wind":{"speed":4.85,"deg":291,"gust":7.13},"visibility":10000,"pop":0,"sys":{"pod":"d"},"dt_txt":"2026-05-20 03:00:00"},{"dt":1779256800,"main":{"temp":42.3,"feels_like":41.21,"temp_min":42.3,"temp_max":42.3,"pressure":999,"sea_level":999,"grnd_level":975,"humidity":16,"temp_kf":0},"weather":[{"id":800,"main":"Clear","description":"clear sky","icon":"01d"}],"clouds":{"all":1},"wind":{"speed":4.3,"deg":274,"gust":5.85},"visibility":10000,"pop":0,"sys":{"pod":"d"},"dt_txt":"2026-05-20 06:00:00"},{"dt":1779267600,"main":{"temp":44.73,"feels_like":42.25,"temp_min":44.73,"temp_max":44.73,"pressure":996,"sea_level":996,"grnd_level":972,"humidity":11,"temp_kf":0},"weather":[{"id":800,"main":"Clear","description":"clear sky","icon":"01d"}],"clouds":{"all":0},"wind":{"speed":3.55,"deg":264,"gust":4.45},"visibility":10000,"pop":0,"sys":{"pod":"d"},"dt_txt":"2026-05-20 09:00:00"},{"dt":1779278400,"main":{"temp":44.66,"feels_like":41.76,"temp_min":44.66,"temp_max":44.66,"pressure":994,"sea_level":994,"grnd_level":971,"humidity":10,"temp_kf":0},"weather":[{"id":800,"main":"Clear","description":"clear sky","icon":"01d"}],"clouds":{"all":0},"wind":{"speed":3.26,"deg":276,"gust":4.72},"visibility":10000,"pop":0,"sys":{"pod":"d"},"dt_txt":"2026-05-20 12:00:00"},{"dt":1779289200,"main":{"temp":41.66,"feels_like":39.73,"temp_min":41.66,"temp_max":41.66,"pressure":995,"sea_level":995,"grnd_level":972,"humidity":14,"temp_kf":0},"weather":[{"id":800,"main":"Clear","description":"clear sky","icon":"01n"}],"clouds":{"all":0},"wind":{"speed":5.13,"deg":297,"gust":8.49},"visibility":10000,"pop":0,"sys":{"pod":"n"},"dt_txt":"2026-05-20 15:00:00"},{"dt":1779300000,"main":{"temp":39.98,"feels_like":37.99,"temp_min":39.98,"temp_max":39.98,"pressure":996,"sea_level":996,"grnd_level":972,"humidity":15,"temp_kf":0},"weather":[{"id":800,"main":"Clear","description":"clear sky","icon":"01n"}],"clouds":{"all":0},"wind":{"speed":4.83,"deg":282,"gust":9.87},"visibility":10000,"pop":0,"sys":{"pod":"n"},"dt_txt":"2026-05-20 18:00:00"},{"dt":1779310800,"main":{"temp":38.09,"feels_like":36.17,"temp_min":38.09,"temp_max":38.09,"pressure":995,"sea_level":995,"grnd_level":971,"humidity":17,"temp_kf":0},"weather":[{"id":800,"main":"Clear","description":"clear sky","icon":"01n"}],"clouds":{"all":0},"wind":{"speed":4.13,"deg":252,"gust":9.14},"visibility":10000,"pop":0,"sys":{"pod":"n"},"dt_txt":"2026-05-20 21:00:00"},{"dt":1779321600,"main":{"temp":35.53,"feels_like":33.52,"temp_min":35.53,"temp_max":35.53,"pressure":997,"sea_level":997,"grnd_level":973,"humidity":19,"temp_kf":0},"weather":[{"id":800,"main":"Clear","description":"clear sky","icon":"01d"}],"clouds":{"all":0},"wind":{"speed":6.69,"deg":268,"gust":13.52},"visibility":10000,"pop":0,"sys":{"pod":"d"},"dt_txt":"2026-05-21 00:00:00"},{"dt":1779332400,"main":{"temp":37.09,"feels_like":35.16,"temp_min":37.09,"temp_max":37.09,"pressure":1000,"sea_level":1000,"grnd_level":976,"humidity":18,"temp_kf":0},"weather":[{"id":800,"main":"Clear","description":"clear sky","icon":"01d"}],"clouds":{"all":0},"wind":{"speed":7.93,"deg":278,"gust":11.65},"visibility":10000,"pop":0,"sys":{"pod":"d"},"dt_txt":"2026-05-21 03:00:00"},{"dt":1779343200,"main":{"temp":41.56,"feels_like":39.32,"temp_min":41.56,"temp_max":41.56,"pressure":1000,"sea_level":1000,"grnd_level":976,"humidity":13,"temp_kf":0},"weather":[{"id":800,"main":"Clear","description":"clear sky","icon":"01d"}],"clouds":{"all":0},"wind":{"speed":6.55,"deg":280,"gust":7.61},"visibility":10000,"pop":0,"sys":{"pod":"d"},"dt_txt":"2026-05-21 06:00:00"},{"dt":1779354000,"main":{"temp":44.14,"feels_like":41.58,"temp_min":44.14,"temp_max":44.14,"pressure":997,"sea_level":997,"grnd_level":973,"humidity":11,"temp_kf":0},"weather":[{"id":800,"main":"Clear","description":"clear sky","icon":"01d"}],"clouds":{"all":0},"wind":{"speed":5.57,"deg":277,"gust":4.83},"visibility":10000,"pop":0,"sys":{"pod":"d"},"dt_txt":"2026-05-21 09:00:00"}],"city":{"id":1271308,"name":"Ghaziabad","coord":{"lat":28.6692,"lon":77.438},"country":"IN","population":1199191,"timezone":19800,"sunrise":1778889548,"sunset":1778938457}}