{"cod":"200","message":0,"cnt":40,"list":[{"dt":1781773200,"main":{"temp":38.88,"feels_like":40.28,"temp_min":38.88,"temp_max":39.51,"pressure":1002,"sea_level":1002,"grnd_level":977,"humidity":28,"temp_kf":-0.63},"weather":[{"id":500,"main":"Rain","description":"light rain","icon":"10d"}],"clouds":{"all":29},"wind":{"speed":3.17,"deg":244,"gust":4.44},"visibility":10000,"pop":0.2,"rain":{"3h":0.18},"sys":{"pod":"d"},"dt_txt":"2026-06-18 09:00:00"},{"dt":1781784000,"main":{"temp":37.54,"feels_like":38.05,"temp_min":37.03,"temp_max":37.54,"pressure":1000,"sea_level":1000,"grnd_level":974,"humidity":28,"temp_kf":0.51},"weather":[{"id":802,"main":"Clouds","description":"scattered clouds","icon":"03d"}],"clouds":{"all":43},"wind":{"speed":7.07,"deg":359,"gust":8.78},"visibility":10000,"pop":0,"sys":{"pod":"d"},"dt_txt":"2026-06-18 12:00:00"},{"dt":1781794800,"main":{"temp":38.93,"feels_like":38.72,"temp_min":38.93,"temp_max":38.93,"pressure":999,"sea_level":999,"grnd_level":975,"humidity":23,"temp_kf":0},"weather":[{"id":804,"main":"Clouds","description":"overcast clouds","icon":"04n"}],"clouds":{"all":90},"wind":{"speed":4.57,"deg":276,"gust":6.9},"visibility":10000,"pop":0,"sys":{"pod":"n"},"dt_txt":"2026-06-18 15:00:00"},{"dt":1781805600,"main":{"temp":36.67,"feels_like":37.5,"temp_min":36.67,"temp_max":36.67,"pressure":1000,"sea_level":1000,"grnd_level":976,"humidity":31,"temp_kf":0},"weather":[{"id":804,"main":"Clouds","description":"overcast clouds","icon":"04n"}],"clouds":{"all":90},"wind":{"speed":4.68,"deg":277,"gust":7.72},"visibility":10000,"pop":0,"sys":{"pod":"n"},"dt_txt":"2026-06-18 18:00:00"},{"dt":1781816400,"main":{"temp":34.74,"feels_like":35.66,"temp_min":34.74,"temp_max":34.74,"pressure":1000,"sea_level":1000,"grnd_level":976,"humidity":36,"temp_kf":0},"weather":[{"id":804,"main":"Clouds","description":"overcast clouds","icon":"04n"}],"clouds":{"all":93},"wind":{"speed":2.3,"deg":290,"gust":3.35},"visibility":10000,"pop":0,"sys":{"pod":"n"},"dt_txt":"2026-06-18 21:00:00"},{"dt":1781827200,"main":{"temp":32.09,"feels_like":33.18,"temp_min":32.09,"temp_max":32.09,"pressure":1002,"sea_level":1002,"grnd_level":977,"humidity":44,"temp_kf":0},"weather":[{"id":803,"main":"Clouds","description":"broken clouds","icon":"04d"}],"clouds":{"all":56},"wind":{"speed":3.28,"deg":282,"gust":6.02},"visibility":10000,"pop":0,"sys":{"pod":"d"},"dt_txt":"2026-06-19 00:00:00"},{"dt":1781838000,"main":{"temp":35.23,"feels_like":35.01,"temp_min":35.23,"temp_max":35.23,"pressure":1003,"sea_level":1003,"grnd_level":979,"humidity":30,"temp_kf":0},"weather":[{"id":800,"main":"Clear","description":"clear sky","icon":"01d"}],"clouds":{"all":5},"wind":{"speed":5.22,"deg":283,"gust":6.33},"visibility":10000,"pop":0,"sys":{"pod":"d"},"dt_txt":"2026-06-19 03:00:00"},{"dt":1781848800,"main":{"temp":39.1,"feels_like":39.61,"temp_min":39.1,"temp_max":39.1,"pressure":1003,"sea_level":1003,"grnd_level":978,"humidity":25,"temp_kf":0},"weather":[{"id":800,"main":"Clear","description":"clear sky","icon":"01d"}],"clouds":{"all":7},"wind":{"speed":4.68,"deg":302,"gust":4.86},"visibility":10000,"pop":0,"sys":{"pod":"d"},"dt_txt":"2026-06-19 06:00:00"},{"dt":1781859600,"main":{"temp":41.47,"feels_like":41.92,"temp_min":41.47,"temp_max":41.47,"pressure":1000,"sea_level":1000,"grnd_level":976,"humidity":21,"temp_kf":0},"weather":[{"id":800,"main":"Clear","description":"clear sky","icon":"01d"}],"clouds":{"all":4},"wind":{"speed":4.4,"deg":282,"gust":5.31},"visibility":10000,"pop":0,"sys":{"pod":"d"},"dt_txt":"2026-06-19 09:00:00"},{"dt":1781870400,"main":{"temp":42.11,"feels_like":41.32,"temp_min":42.11,"temp_max":42.11,"pressure":998,"sea_level":998,"grnd_level":974,"humidity":17,"temp_kf":0},"weather":[{"id":800,"main":"Clear","description":"clear sky","icon":"01d"}],"clouds":{"all":5},"wind":{"speed":4.31,"deg":299,"gust":5.44},"visibility":10000,"pop":0,"sys":{"pod":"d"},"dt_txt":"2026-06-19 12:00:00"},{"dt":1781881200,"main":{"temp":36.4,"feels_like":38.24,"temp_min":36.4,"temp_max":36.4,"pressure":1000,"sea_level":1000,"grnd_level":976,"humidity":35,"temp_kf":0},"weather":[{"id":800,"main":"Clear","description":"clear sky","icon":"01n"}],"clouds":{"all":0},"wind":{"speed":6.68,"deg":289,"gust":12.12},"visibility":10000,"pop":0,"sys":{"pod":"n"},"dt_txt":"2026-06-19 15:00:00"},{"dt":1781892000,"main":{"temp":36.09,"feels_like":36.3,"temp_min":36.09,"temp_max":36.09,"pressure":1000,"sea_level":1000,"grnd_level":976,"humidity":30,"temp_kf":0},"weather":[{"id":800,"main":"Clear","description":"clear sky","icon":"01n"}],"clouds":{"all":1},"wind":{"speed":5.14,"deg":299,"gust":10.51},"visibility":10000,"pop":0,"sys":{"pod":"n"},"dt_txt":"2026-06-19 18:00:00"},{"dt":1781902800,"main":{"temp":35.77,"feels_like":35.58,"temp_min":35.77,"temp_max":35.77,"pressure":999,"sea_level":999,"grnd_level":975,"humidity":29,"temp_kf":0},"weather":[{"id":803,"main":"Clouds","description":"broken clouds","icon":"04n"}],"clouds":{"all":70},"wind":{"speed":3.57,"deg":289,"gust":8.41},"visibility":10000,"pop":0,"sys":{"pod":"n"},"dt_txt":"2026-06-19 21:00:00"},{"dt":1781913600,"main":{"temp":35.7,"feels_like":35.7,"temp_min":35.7,"temp_max":35.7,"pressure":1000,"sea_level":1000,"grnd_level":976,"humidity":30,"temp_kf":0},"weather":[{"id":803,"main":"Clouds","description":"broken clouds","icon":"04d"}],"clouds":{"all":76},"wind":{"speed":3.93,"deg":281,"gust":9.26},"visibility":10000,"pop":0,"sys":{"pod":"d"},"dt_txt":"2026-06-20 00:00:00"},{"dt":1781924400,"main":{"temp":36.06,"feels_like":37.63,"temp_min":36.06,"temp_max":36.06,"pressure":1002,"sea_level":1002,"grnd_level":978,"humidity":35,"temp_kf":0},"weather":[{"id":803,"main":"Clouds","description":"broken clouds","icon":"04d"}],"clouds":{"all":67},"wind":{"speed":7.43,"deg":279,"gust":11.36},"visibility":10000,"pop":0,"sys":{"pod":"d"},"dt_txt":"2026-06-20 03:00:00"},{"dt":1781935200,"main":{"temp":37.81,"feels_like":39.8,"temp_min":37.81,"temp_max":37.81,"pressure":1002,"sea_level":1002,"grnd_level":978,"humidity":32,"temp_kf":0},"weather":[{"id":804,"main":"Clouds","description":"overcast clouds","icon":"04d"}],"clouds":{"all":86},"wind":{"speed":6.29,"deg":276,"gust":9.38},"visibility":10000,"pop":0,"sys":{"pod":"d"},"dt_txt":"2026-06-20 06:00:00"},{"dt":1781946000,"main":{"temp":41.8,"feels_like":42.86,"temp_min":41.8,"temp_max":41.8,"pressure":999,"sea_level":999,"grnd_level":975,"humidity":22,"temp_kf":0},"weather":[{"id":802,"main":"Clouds","description":"scattered clouds","icon":"03d"}],"clouds":{"all":41},"wind":{"speed":6.83,"deg":270,"gust":7.49},"visibility":10000,"pop":0,"sys":{"pod":"d"},"dt_txt":"2026-06-20 09:00:00"},{"dt":1781956800,"main":{"temp":42.26,"feels_like":43.17,"temp_min":42.26,"temp_max":42.26,"pressure":997,"sea_level":997,"grnd_level":973,"humidity":21,"temp_kf":0},"weather":[{"id":802,"main":"Clouds","description":"scattered clouds","icon":"03d"}],"clouds":{"all":47},"wind":{"speed":7.18,"deg":275,"gust":6.28},"visibility":10000,"pop":0,"sys":{"pod":"d"},"dt_txt":"2026-06-20 12:00:00"},{"dt":1781967600,"main":{"temp":40.3,"feels_like":40.83,"temp_min":40.3,"temp_max":40.3,"pressure":998,"sea_level":998,"grnd_level":975,"humidity":23,"temp_kf":0},"weather":[{"id":803,"main":"Clouds","description":"broken clouds","icon":"04n"}],"clouds":{"all":61},"wind":{"speed":7.11,"deg":271,"gust":9.08},"visibility":10000,"pop":0,"sys":{"pod":"n"},"dt_txt":"2026-06-20 15:00:00"},{"dt":1781978400,"main":{"temp":38.21,"feels_like":38.82,"temp_min":38.21,"temp_max":38.21,"pressure":1000,"sea_level":1000,"grnd_level":976,"humidity":27,"temp_kf":0},"weather":[{"id":803,"main":"Clouds","description":"broken clouds","icon":"04n"}],"clouds":{"all":53},"wind":{"speed":6.55,"deg":278,"gust":11.48},"visibility":10000,"pop":0,"sys":{"pod":"n"},"dt_txt":"2026-06-20 18:00:00"},{"dt":1781989200,"main":{"temp":35.12,"feels_like":34.64,"temp_min":35.12,"temp_max":35.12,"pressure":999,"sea_level":999,"grnd_level":975,"humidity":29,"temp_kf":0},"weather":[{"id":800,"main":"Clear","description":"clear sky","icon":"01n"}],"clouds":{"all":10},"wind":{"speed":3.28,"deg":318,"gust":7.69},"visibility":10000,"pop":0,"sys":{"pod":"n"},"dt_txt":"2026-06-20 21:00:00"},{"dt":1782000000,"main":{"temp":34.58,"feels_like":34.08,"temp_min":34.58,"temp_max":34.58,"pressure":999,"sea_level":999,"grnd_level":975,"humidity":30,"temp_kf":0},"weather":[{"id":800,"main":"Clear","description":"clear sky","icon":"01d"}],"clouds":{"all":3},"wind":{"speed":2.81,"deg":272,"gust":6.97},"visibility":10000,"pop":0,"sys":{"pod":"d"},"dt_txt":"2026-06-21 00:00:00"},{"dt":1782010800,"main":{"temp":36.39,"feels_like":37.91,"temp_min":36.39,"temp_max":36.39,"pressure":1001,"sea_level":1001,"grnd_level":977,"humidity":34,"temp_kf":0},"weather":[{"id":802,"main":"Clouds","description":"scattered clouds","icon":"03d"}],"clouds":{"all":31},"wind":{"speed":5.58,"deg":278,"gust":7.7},"visibility":10000,"pop":0,"sys":{"pod":"d"},"dt_txt":"2026-06-21 03:00:00"},{"dt":1782021600,"main":{"temp":40.41,"feels_like":41.78,"temp_min":40.41,"temp_max":40.41,"pressure":1001,"sea_level":1001,"grnd_level":977,"humidity":25,"temp_kf":0},"weather":[{"id":801,"main":"Clouds","description":"few clouds","icon":"02d"}],"clouds":{"all":15},"wind":{"speed":6.15,"deg":279,"gust":6.39},"visibility":10000,"pop":0,"sys":{"pod":"d"},"dt_txt":"2026-06-21 06:00:00"},{"dt":1782032400,"main":{"temp":42.78,"feels_like":42.26,"temp_min":42.78,"temp_max":42.78,"pressure":998,"sea_level":998,"grnd_level":974,"humidity":17,"temp_kf":0},"weather":[{"id":800,"main":"Clear","description":"clear sky","icon":"01d"}],"clouds":{"all":0},"wind":{"speed":5.81,"deg":259,"gust":6.59},"visibility":10000,"pop":0,"sys":{"pod":"d"},"dt_txt":"2026-06-21 09:00:00"},{"dt":1782043200,"main":{"temp":42.29,"feels_like":41.2,"temp_min":42.29,"temp_max":42.29,"pressure":996,"sea_level":996,"grnd_level":972,"humidity":16,"temp_kf":0},"weather":[{"id":801,"main":"Clouds","description":"few clouds","icon":"02d"}],"clouds":{"all":20},"wind":{"speed":5.01,"deg":277,"gust":4.89},"visibility":10000,"pop":0,"sys":{"pod":"d"},"dt_txt":"2026-06-21 12:00:00"},{"dt":1782054000,"main":{"temp":39.55,"feels_like":39.99,"temp_min":39.55,"temp_max":39.55,"pressure":997,"sea_level":997,"grnd_level":974,"humidity":24,"temp_kf":0},"weather":[{"id":803,"main":"Clouds","description":"broken clouds","icon":"04n"}],"clouds":{"all":74},"wind":{"speed":5.33,"deg":282,"gust":7.51},"visibility":10000,"pop":0,"sys":{"pod":"n"},"dt_txt":"2026-06-21 15:00:00"},{"dt":1782064800,"main":{"temp":37.76,"feels_like":38.1,"temp_min":37.76,"temp_max":37.76,"pressure":999,"sea_level":999,"grnd_level":975,"humidity":27,"temp_kf":0},"weather":[{"id":804,"main":"Clouds","description":"overcast clouds","icon":"04n"}],"clouds":{"all":87},"wind":{"speed":4.24,"deg":293,"gust":8.6},"visibility":10000,"pop":0,"sys":{"pod":"n"},"dt_txt":"2026-06-21 18:00:00"},{"dt":1782075600,"main":{"temp":36.73,"feels_like":36.78,"temp_min":36.73,"temp_max":36.73,"pressure":998,"sea_level":998,"grnd_level":974,"humidity":28,"temp_kf":0},"weather":[{"id":804,"main":"Clouds","description":"overcast clouds","icon":"04n"}],"clouds":{"all":100},"wind":{"speed":2.56,"deg":298,"gust":5.83},"visibility":10000,"pop":0,"sys":{"pod":"n"},"dt_txt":"2026-06-21 21:00:00"},{"dt":1782086400,"main":{"temp":35.93,"feels_like":35.58,"temp_min":35.93,"temp_max":35.93,"pressure":999,"sea_level":999,"grnd_level":975,"humidity":28,"temp_kf":0},"weather":[{"id":804,"main":"Clouds","description":"overcast clouds","icon":"04d"}],"clouds":{"all":100},"wind":{"speed":4.67,"deg":279,"gust":8.48},"visibility":10000,"pop":0,"sys":{"pod":"d"},"dt_txt":"2026-06-22 00:00:00"},{"dt":1782097200,"main":{"temp":36.74,"feels_like":37.91,"temp_min":36.74,"temp_max":36.74,"pressure":1000,"sea_level":1000,"grnd_level":976,"humidity":32,"temp_kf":0},"weather":[{"id":800,"main":"Clear","description":"clear sky","icon":"01d"}],"clouds":{"all":0},"wind":{"speed":7.78,"deg":279,"gust":10.14},"visibility":10000,"pop":0,"sys":{"pod":"d"},"dt_txt":"2026-06-22 03:00:00"},{"dt":1782108000,"main":{"temp":40.66,"feels_like":42.21,"temp_min":40.66,"temp_max":40.66,"pressure":999,"sea_level":999,"grnd_level":975,"humidity":25,"temp_kf":0},"weather":[{"id":800,"main":"Clear","description":"clear sky","icon":"01d"}],"clouds":{"all":4},"wind":{"speed":6.78,"deg":277,"gust":7.31},"visibility":10000,"pop":0,"sys":{"pod":"d"},"dt_txt":"2026-06-22 06:00:00"},{"dt":1782118800,"main":{"temp":42.51,"feels_like":43.13,"temp_min":42.51,"temp_max":42.51,"pressure":996,"sea_level":996,"grnd_level":972,"humidity":20,"temp_kf":0},"weather":[{"id":801,"main":"Clouds","description":"few clouds","icon":"02d"}],"clouds":{"all":18},"wind":{"speed":6.81,"deg":272,"gust":7.25},"visibility":10000,"pop":0,"sys":{"pod":"d"},"dt_txt":"2026-06-22 09:00:00"},{"dt":1782129600,"main":{"temp":40.36,"feels_like":41.3,"temp_min":40.36,"temp_max":40.36,"pressure":995,"sea_level":995,"grnd_level":971,"humidity":24,"temp_kf":0},"weather":[{"id":500,"main":"Rain","description":"light rain","icon":"10d"}],"clouds":{"all":34},"wind":{"speed":5.63,"deg":250,"gust":7.57},"visibility":10000,"pop":0.2,"rain":{"3h":0.11},"sys":{"pod":"d"},"dt_txt":"2026-06-22 12:00:00"},{"dt":1782140400,"main":{"temp":34.79,"feels_like":35.25,"temp_min":34.79,"temp_max":34.79,"pressure":998,"sea_level":998,"grnd_level":974,"humidity":34,"temp_kf":0},"weather":[{"id":500,"main":"Rain","description":"light rain","icon":"10n"}],"clouds":{"all":50},"wind":{"speed":5.67,"deg":244,"gust":10.36},"visibility":10000,"pop":0.39,"rain":{"3h":0.13},"sys":{"pod":"n"},"dt_txt":"2026-06-22 15:00:00"},{"dt":1782151200,"main":{"temp":36.34,"feels_like":36.43,"temp_min":36.34,"temp_max":36.34,"pressure":998,"sea_level":998,"grnd_level":974,"humidity":29,"temp_kf":0},"weather":[{"id":803,"main":"Clouds","description":"broken clouds","icon":"04n"}],"clouds":{"all":68},"wind":{"speed":3.66,"deg":284,"gust":9.65},"visibility":10000,"pop":0,"sys":{"pod":"n"},"dt_txt":"2026-06-22 18:00:00"},{"dt":1782162000,"main":{"temp":36.78,"feels_like":37.12,"temp_min":36.78,"temp_max":36.78,"pressure":996,"sea_level":996,"grnd_level":972,"humidity":29,"temp_kf":0},"weather":[{"id":804,"main":"Clouds","description":"overcast clouds","icon":"04n"}],"clouds":{"all":93},"wind":{"speed":5.32,"deg":271,"gust":11.21},"visibility":10000,"pop":0,"sys":{"pod":"n"},"dt_txt":"2026-06-22 21:00:00"},{"dt":1782172800,"main":{"temp":34.89,"feels_like":34.94,"temp_min":34.89,"temp_max":34.89,"pressure":997,"sea_level":997,"grnd_level":973,"humidity":32,"temp_kf":0},"weather":[{"id":500,"main":"Rain","description":"light rain","icon":"10d"}],"clouds":{"all":58},"wind":{"speed":5.55,"deg":284,"gust":11.29},"visibility":10000,"pop":0.85,"rain":{"3h":0.91},"sys":{"pod":"d"},"dt_txt":"2026-06-23 00:00:00"},{"dt":1782183600,"main":{"temp":37.01,"feels_like":37.77,"temp_min":37.01,"temp_max":37.01,"pressure":998,"sea_level":998,"grnd_level":974,"humidity":30,"temp_kf":0},"weather":[{"id":800,"main":"Clear","description":"clear sky","icon":"01d"}],"clouds":{"all":2},"wind":{"speed":6.8,"deg":286,"gust":8.38},"visibility":10000,"pop":0,"sys":{"pod":"d"},"dt_txt":"2026-06-23 03:00:00"},{"dt":1782194400,"main":{"temp":40.98,"feels_like":41.54,"temp_min":40.98,"temp_max":40.98,"pressure":997,"sea_level":997,"grnd_level":974,"humidity":22,"temp_kf":0},"weather":[{"id":800,"main":"Clear","description":"clear sky","icon":"01d"}],"clouds":{"all":6},"wind":{"speed":7.15,"deg":290,"gust":8.53},"visibility":10000,"pop":0,"sys":{"pod":"d"},"dt_txt":"2026-06-23 06:00:00"}],"city":{"id":1271308,"name":"Ghaziabad","coord":{"lat":28.6692,"lon":77.438},"country":"IN","population":1199191,"timezone":19800,"sunrise":1781740339,"sunset":1781790619}}