{"coord":{"lon":77.438,"lat":28.6692},"weather":[{"id":804,"main":"Clouds","description":"overcast clouds","icon":"04n"}],"base":"stations","main":{"temp":28.32,"feels_like":26.85,"temp_min":28.32,"temp_max":28.32,"pressure":1007,"humidity":10,"sea_level":1007,"grnd_level":982},"visibility":10000,"wind":{"speed":1.6,"deg":260,"gust":1.63},"clouds":{"all":100},"dt":1773753040,"sys":{"country":"IN","sunrise":1773709090,"sunset":1773752360},"timezone":19800,"id":1271308,"name":"Ghaziabad","cod":200}