{"coord":{"lon":77.438,"lat":28.6692},"weather":[{"id":804,"main":"Clouds","description":"overcast clouds","icon":"04d"}],"base":"stations","main":{"temp":33.59,"feels_like":31.1,"temp_min":33.59,"temp_max":33.59,"pressure":1008,"humidity":10,"sea_level":1008,"grnd_level":983},"visibility":10000,"wind":{"speed":2.83,"deg":273,"gust":2.81},"clouds":{"all":93},"dt":1773828570,"sys":{"country":"IN","sunrise":1773795420,"sunset":1773838794},"timezone":19800,"id":1271308,"name":"Ghaziabad","cod":200}