{"data":{"time":"2026-03-07T16:45:00Z","values":{"altimeterSetting":1013.22,"cloudBase":null,"cloudCeiling":null,"cloudCover":0,"dewPoint":18,"freezingRainIntensity":0,"humidity":76,"precipitationProbability":0,"pressureSeaLevel":1012.63,"pressureSurfaceLevel":988.75,"rainIntensity":0,"sleetIntensity":0,"snowIntensity":0,"temperature":22.49,"temperatureApparent":22.5,"uvHealthConcern":0,"uvIndex":0,"visibility":16,"weatherCode":1000,"windDirection":148,"windGust":1,"windSpeed":0.4}},"location":{"lat":28.6692,"lon":77.438}}