{"data":{"time":"2026-02-15T09:27:00Z","values":{"altimeterSetting":1012.89,"cloudBase":null,"cloudCeiling":null,"cloudCover":0,"dewPoint":8.3,"freezingRainIntensity":0,"humidity":31,"precipitationProbability":0,"pressureSeaLevel":1012.43,"pressureSurfaceLevel":988.43,"rainIntensity":0,"sleetIntensity":0,"snowIntensity":0,"temperature":26.86,"temperatureApparent":26.4,"uvHealthConcern":1,"uvIndex":3,"visibility":16,"weatherCode":1000,"windDirection":305,"windGust":8.1,"windSpeed":3.3}},"location":{"lat":28.6692,"lon":77.438}}