{"data":{"time":"2026-03-16T11:14:00Z","values":{"altimeterSetting":1005.9,"cloudBase":2.93,"cloudCeiling":null,"cloudCover":8.59,"dewPoint":12.9,"freezingRainIntensity":0,"humidity":44,"precipitationProbability":0,"pressureSeaLevel":1005.53,"pressureSurfaceLevel":981.58,"rainIntensity":0,"sleetIntensity":0,"snowIntensity":0,"temperature":25.99,"temperatureApparent":26,"uvHealthConcern":0,"uvIndex":0,"visibility":16,"weatherCode":1000,"windDirection":53,"windGust":9.6,"windSpeed":4.2}},"location":{"lat":28.6692,"lon":77.438}}