{"data":{"time":"2026-03-09T05:47:00Z","values":{"altimeterSetting":1012.93,"cloudBase":null,"cloudCeiling":null,"cloudCover":42.97,"dewPoint":17.4,"freezingRainIntensity":0,"humidity":44,"precipitationProbability":0,"pressureSeaLevel":1012.39,"pressureSurfaceLevel":988.47,"rainIntensity":0,"sleetIntensity":0,"snowIntensity":0,"temperature":31.12,"temperatureApparent":31.7,"uvHealthConcern":2,"uvIndex":7,"visibility":16,"weatherCode":1101,"windDirection":308,"windGust":7,"windSpeed":2.5}},"location":{"lat":28.6692,"lon":77.438}}