{"data":{"time":"2026-04-19T14:56:00Z","values":{"altimeterSetting":1005.73,"cloudBase":null,"cloudCeiling":null,"cloudCover":0.61,"dewPoint":5.8,"freezingRainIntensity":0,"humidity":19,"precipitationProbability":0,"pressureSeaLevel":1004.83,"pressureSurfaceLevel":981.41,"rainIntensity":0,"sleetIntensity":0,"snowIntensity":0,"temperature":32.37,"temperatureApparent":30.3,"uvHealthConcern":0,"uvIndex":0,"visibility":16,"weatherCode":1000,"windDirection":278,"windGust":1.9,"windSpeed":1.2}},"location":{"lat":28.6692,"lon":77.438}}