{"data":{"time":"2026-04-10T06:11:00Z","values":{"altimeterSetting":1014.7,"cloudBase":null,"cloudCeiling":null,"cloudCover":0,"dewPoint":10.5,"freezingRainIntensity":0,"humidity":36,"precipitationProbability":0,"pressureSeaLevel":1014.25,"pressureSurfaceLevel":990.2,"rainIntensity":0,"sleetIntensity":0,"snowIntensity":0,"temperature":26.78,"temperatureApparent":26.5,"uvHealthConcern":3,"uvIndex":8,"visibility":16,"weatherCode":1000,"windDirection":300,"windGust":11.4,"windSpeed":4.9}},"location":{"lat":28.6692,"lon":77.438}}