{"data":{"time":"2026-06-27T18:47:00Z","values":{"altimeterSetting":1000.4,"cloudBase":3.67,"cloudCeiling":null,"cloudCover":1.53,"dewPoint":22.9,"freezingRainIntensity":0,"humidity":60,"precipitationProbability":0,"pressureSeaLevel":997.56,"pressureSurfaceLevel":976.19,"rainIntensity":0,"sleetIntensity":0,"snowIntensity":0,"temperature":31.69,"temperatureApparent":36.3,"uvHealthConcern":0,"uvIndex":0,"visibility":11.8,"weatherCode":1000,"windDirection":175,"windGust":2.4,"windSpeed":0.3}},"location":{"lat":28.6692,"lon":77.438}}