{"data":{"time":"2026-02-13T11:49:00Z","values":{"altimeterSetting":1014.47,"cloudBase":null,"cloudCeiling":null,"cloudCover":7.03,"dewPoint":11.2,"freezingRainIntensity":0,"humidity":52,"precipitationProbability":0,"pressureSeaLevel":1014.16,"pressureSurfaceLevel":989.98,"rainIntensity":0,"sleetIntensity":0,"snowIntensity":0,"temperature":21.39,"temperatureApparent":21.4,"uvHealthConcern":0,"uvIndex":0,"visibility":16,"weatherCode":1000,"windDirection":335,"windGust":3.1,"windSpeed":1.5}},"location":{"lat":28.6692,"lon":77.438}}