{"data":{"time":"2026-03-19T21:57:00Z","values":{"altimeterSetting":1010.58,"cloudBase":3.28,"cloudCeiling":2.7,"cloudCover":100,"dewPoint":15.2,"freezingRainIntensity":0,"humidity":90,"precipitationProbability":24,"pressureSeaLevel":1010.38,"pressureSurfaceLevel":986.17,"rainIntensity":0.4,"sleetIntensity":0,"snowIntensity":0,"temperature":16.8,"temperatureApparent":16.8,"uvHealthConcern":0,"uvIndex":0,"visibility":16,"weatherCode":4000,"windDirection":287,"windGust":2.7,"windSpeed":1.5}},"location":{"lat":28.6692,"lon":77.438}}