{"data":{"time":"2026-02-17T06:40:00Z","values":{"altimeterSetting":1016.33,"cloudBase":null,"cloudCeiling":null,"cloudCover":0,"dewPoint":12.8,"freezingRainIntensity":0,"humidity":44,"precipitationProbability":0,"pressureSeaLevel":1016.01,"pressureSurfaceLevel":991.8,"rainIntensity":0,"sleetIntensity":0,"snowIntensity":0,"temperature":25.75,"temperatureApparent":25.8,"uvHealthConcern":2,"uvIndex":6,"visibility":16,"weatherCode":1000,"windDirection":129,"windGust":7,"windSpeed":2.5}},"location":{"lat":28.6692,"lon":77.438}}