{"data":{"time":"2026-04-16T20:26:00Z","values":{"altimeterSetting":1006.96,"cloudBase":7.6,"cloudCeiling":8,"cloudCover":100,"dewPoint":12.3,"freezingRainIntensity":0,"humidity":44,"precipitationProbability":0,"pressureSeaLevel":1006.18,"pressureSurfaceLevel":982.62,"rainIntensity":0,"sleetIntensity":0,"snowIntensity":0,"temperature":25.31,"temperatureApparent":25.3,"uvHealthConcern":0,"uvIndex":0,"visibility":16,"weatherCode":1001,"windDirection":154,"windGust":1.2,"windSpeed":0.7}},"location":{"lat":28.6692,"lon":77.438}}