{"data":{"time":"2026-06-27T22:30:00Z","values":{"altimeterSetting":999.86,"cloudBase":1.96,"cloudCeiling":null,"cloudCover":25.41,"dewPoint":24.3,"freezingRainIntensity":0,"humidity":71,"precipitationProbability":0,"pressureSeaLevel":996.29,"pressureSurfaceLevel":975.66,"rainIntensity":0,"sleetIntensity":0,"snowIntensity":0,"temperature":30.08,"temperatureApparent":35.4,"uvHealthConcern":0,"uvIndex":0,"visibility":11.1,"weatherCode":1100,"windDirection":181,"windGust":2,"windSpeed":0.1}},"location":{"lat":28.6692,"lon":77.438}}