{"data":{"time":"2026-07-14T22:10:00Z","values":{"altimeterSetting":1000.64,"cloudBase":4.45,"cloudCeiling":null,"cloudCover":34.4,"dewPoint":26.1,"freezingRainIntensity":0,"humidity":89,"precipitationProbability":0,"pressureSeaLevel":998.28,"pressureSurfaceLevel":976.42,"rainIntensity":0,"sleetIntensity":0,"snowIntensity":0,"temperature":28.21,"temperatureApparent":34.1,"uvHealthConcern":0,"uvIndex":0,"visibility":11.3,"weatherCode":1100,"windDirection":269,"windGust":3.5,"windSpeed":0.3}},"location":{"lat":28.6692,"lon":77.438}}