{"data":{"time":"2026-04-08T14:20:00Z","values":{"altimeterSetting":1010.28,"cloudBase":2.69,"cloudCeiling":null,"cloudCover":12.5,"dewPoint":14.6,"freezingRainIntensity":0,"humidity":77,"precipitationProbability":0,"pressureSeaLevel":1010.15,"pressureSurfaceLevel":985.87,"rainIntensity":0,"sleetIntensity":0,"snowIntensity":0,"temperature":18.63,"temperatureApparent":18.6,"uvHealthConcern":0,"uvIndex":0,"visibility":16,"weatherCode":1100,"windDirection":100,"windGust":3.2,"windSpeed":1.6}},"location":{"lat":28.6692,"lon":77.438}}