{"data":{"time":"2026-03-25T14:20:00Z","values":{"altimeterSetting":1009.39,"cloudBase":8.88,"cloudCeiling":9.4,"cloudCover":75,"dewPoint":15.2,"freezingRainIntensity":0,"humidity":56,"precipitationProbability":0,"pressureSeaLevel":1008.87,"pressureSurfaceLevel":985,"rainIntensity":0,"sleetIntensity":0,"snowIntensity":0,"temperature":24.49,"temperatureApparent":24.5,"uvHealthConcern":0,"uvIndex":0,"visibility":16,"weatherCode":1001,"windDirection":321,"windGust":1.6,"windSpeed":1}},"location":{"lat":28.6692,"lon":77.438}}