{"data":{"time":"2026-07-17T17:43:00Z","values":{"altimeterSetting":1001.37,"cloudBase":1.41,"cloudCeiling":10.5,"cloudCover":89.18,"dewPoint":26.5,"freezingRainIntensity":0,"humidity":78,"precipitationProbability":0,"pressureSeaLevel":999.24,"pressureSurfaceLevel":977.66,"rainIntensity":0,"sleetIntensity":0,"snowIntensity":0,"temperature":30.05,"temperatureApparent":37.3,"uvHealthConcern":0,"uvIndex":0,"visibility":9.2,"weatherCode":1001,"windDirection":163,"windGust":1.7,"windSpeed":0.4}},"location":{"lat":28.6692,"lon":77.438}}