{"data":{"time":"2026-04-11T15:56:00Z","values":{"altimeterSetting":1010.32,"cloudBase":3.02,"cloudCeiling":null,"cloudCover":23.44,"dewPoint":12,"freezingRainIntensity":0,"humidity":47,"precipitationProbability":0,"pressureSeaLevel":1009.29,"pressureSurfaceLevel":985.91,"rainIntensity":0,"sleetIntensity":0,"snowIntensity":0,"temperature":23.86,"temperatureApparent":23.9,"uvHealthConcern":0,"uvIndex":0,"visibility":16,"weatherCode":1100,"windDirection":40,"windGust":1.7,"windSpeed":0.9}},"location":{"lat":28.6692,"lon":77.438}}