{"data":{"time":"2026-02-28T14:32:00Z","values":{"altimeterSetting":1008.16,"cloudBase":null,"cloudCeiling":null,"cloudCover":0,"dewPoint":12.1,"freezingRainIntensity":0,"humidity":52,"precipitationProbability":0,"pressureSeaLevel":1007.58,"pressureSurfaceLevel":983.79,"rainIntensity":0,"sleetIntensity":0,"snowIntensity":0,"temperature":22.4,"temperatureApparent":22.4,"uvHealthConcern":0,"uvIndex":0,"visibility":16,"weatherCode":1000,"windDirection":323,"windGust":1.6,"windSpeed":1}},"location":{"lat":28.6692,"lon":77.438}}