{"data":{"time":"2026-04-16T13:23:00Z","values":{"altimeterSetting":1004.82,"cloudBase":7.69,"cloudCeiling":10.3,"cloudCover":100,"dewPoint":6.2,"freezingRainIntensity":0,"humidity":18,"precipitationProbability":0,"pressureSeaLevel":1003.98,"pressureSurfaceLevel":980.52,"rainIntensity":0,"sleetIntensity":0,"snowIntensity":0,"temperature":34.1,"temperatureApparent":31.9,"uvHealthConcern":0,"uvIndex":0,"visibility":16,"weatherCode":1001,"windDirection":341,"windGust":7,"windSpeed":3.6}},"location":{"lat":28.6692,"lon":77.438}}