{
  "lastUpdated": "2026-05-25T17:22:57Z",
  "lastUpdatedIST": "2026-05-25 22:52:57 IST",
  "timestamp": 1779729777,
  "refreshInterval": "5 minutes",
  "source": "GitHub Actions",
  "openweather": {
    "coord": {
      "lon": 77.438,
      "lat": 28.6692
    },
    "weather": [
      {
        "id": 800,
        "main": "Clear",
        "description": "clear sky",
        "icon": "01n"
      }
    ],
    "base": "stations",
    "main": {
      "temp": 39.39,
      "feels_like": 36.13,
      "temp_min": 39.39,
      "temp_max": 39.39,
      "pressure": 999,
      "humidity": 8,
      "sea_level": 999,
      "grnd_level": 975
    },
    "visibility": 10000,
    "wind": {
      "speed": 3.65,
      "deg": 288,
      "gust": 9.09
    },
    "clouds": {
      "all": 0
    },
    "dt": 1779729777,
    "sys": {
      "country": "IN",
      "sunrise": 1779666897,
      "sunset": 1779716380
    },
    "timezone": 19800,
    "id": 1271308,
    "name": "Ghaziabad",
    "cod": 200
  },
  "airPollution": {
    "coord": {
      "lon": 77.438,
      "lat": 28.6692
    },
    "list": [
      {
        "main": {
          "aqi": 3
        },
        "components": {
          "co": 228.56,
          "no": 0,
          "no2": 8.91,
          "o3": 89.9,
          "so2": 3.53,
          "pm2_5": 21.94,
          "pm10": 62.91,
          "nh3": 34.24
        },
        "dt": 1779729777
      }
    ]
  },
  "forecast": {
    "cod": "200",
    "message": 0,
    "cnt": 40,
    "list": [
      {
        "dt": 1779732000,
        "main": {
          "temp": 38.86,
          "feels_like": 35.77,
          "temp_min": 38.86,
          "temp_max": 38.86,
          "pressure": 998,
          "sea_level": 998,
          "grnd_level": 974,
          "humidity": 9,
          "temp_kf": 0
        },
        "weather": [
          {
            "id": 800,
            "main": "Clear",
            "description": "clear sky",
            "icon": "01n"
          }
        ],
        "clouds": {
          "all": 0
        },
        "wind": {
          "speed": 3.73,
          "deg": 287,
          "gust": 8.95
        },
        "visibility": 10000,
        "pop": 0,
        "sys": {
          "pod": "n"
        },
        "dt_txt": "2026-05-25 18:00:00"
      },
      {
        "dt": 1779742800,
        "main": {
          "temp": 37.74,
          "feels_like": 34.83,
          "temp_min": 35.5,
          "temp_max": 37.74,
          "pressure": 998,
          "sea_level": 998,
          "grnd_level": 974,
          "humidity": 10,
          "temp_kf": 2.24
        },
        "weather": [
          {
            "id": 800,
            "main": "Clear",
            "description": "clear sky",
            "icon": "01n"
          }
        ],
        "clouds": {
          "all": 0
        },
        "wind": {
          "speed": 3.71,
          "deg": 313,
          "gust": 9.81
        },
        "visibility": 10000,
        "pop": 0,
        "sys": {
          "pod": "n"
        },
        "dt_txt": "2026-05-25 21:00:00"
      },
      {
        "dt": 1779753600,
        "main": {
          "temp": 35.37,
          "feels_like": 32.8,
          "temp_min": 33.63,
          "temp_max": 35.37,
          "pressure": 999,
          "sea_level": 999,
          "grnd_level": 976,
          "humidity": 13,
          "temp_kf": 1.74
        },
        "weather": [
          {
            "id": 800,
            "main": "Clear",
            "description": "clear sky",
            "icon": "01d"
          }
        ],
        "clouds": {
          "all": 0
        },
        "wind": {
          "speed": 2.84,
          "deg": 291,
          "gust": 5.6
        },
        "visibility": 10000,
        "pop": 0,
        "sys": {
          "pod": "d"
        },
        "dt_txt": "2026-05-26 00:00:00"
      },
      {
        "dt": 1779764400,
        "main": {
          "temp": 37.59,
          "feels_like": 34.61,
          "temp_min": 37.59,
          "temp_max": 37.59,
          "pressure": 1002,
          "sea_level": 1002,
          "grnd_level": 978,
          "humidity": 9,
          "temp_kf": 0
        },
        "weather": [
          {
            "id": 800,
            "main": "Clear",
            "description": "clear sky",
            "icon": "01d"
          }
        ],
        "clouds": {
          "all": 0
        },
        "wind": {
          "speed": 4.32,
          "deg": 269,
          "gust": 5.56
        },
        "visibility": 10000,
        "pop": 0,
        "sys": {
          "pod": "d"
        },
        "dt_txt": "2026-05-26 03:00:00"
      },
      {
        "dt": 1779775200,
        "main": {
          "temp": 43.06,
          "feels_like": 39.77,
          "temp_min": 43.06,
          "temp_max": 43.06,
          "pressure": 1002,
          "sea_level": 1002,
          "grnd_level": 978,
          "humidity": 9,
          "temp_kf": 0
        },
        "weather": [
          {
            "id": 800,
            "main": "Clear",
            "description": "clear sky",
            "icon": "01d"
          }
        ],
        "clouds": {
          "all": 0
        },
        "wind": {
          "speed": 5.01,
          "deg": 275,
          "gust": 6.99
        },
        "visibility": 10000,
        "pop": 0,
        "sys": {
          "pod": "d"
        },
        "dt_txt": "2026-05-26 06:00:00"
      },
      {
        "dt": 1779786000,
        "main": {
          "temp": 45.32,
          "feels_like": 40.85,
          "temp_min": 45.32,
          "temp_max": 45.32,
          "pressure": 999,
          "sea_level": 999,
          "grnd_level": 975,
          "humidity": 6,
          "temp_kf": 0
        },
        "weather": [
          {
            "id": 800,
            "main": "Clear",
            "description": "clear sky",
            "icon": "01d"
          }
        ],
        "clouds": {
          "all": 0
        },
        "wind": {
          "speed": 4.92,
          "deg": 272,
          "gust": 8.78
        },
        "visibility": 10000,
        "pop": 0,
        "sys": {
          "pod": "d"
        },
        "dt_txt": "2026-05-26 09:00:00"
      },
      {
        "dt": 1779796800,
        "main": {
          "temp": 44.76,
          "feels_like": 40.72,
          "temp_min": 44.76,
          "temp_max": 44.76,
          "pressure": 997,
          "sea_level": 997,
          "grnd_level": 973,
          "humidity": 7,
          "temp_kf": 0
        },
        "weather": [
          {
            "id": 800,
            "main": "Clear",
            "description": "clear sky",
            "icon": "01d"
          }
        ],
        "clouds": {
          "all": 3
        },
        "wind": {
          "speed": 6.44,
          "deg": 286,
          "gust": 9.54
        },
        "visibility": 10000,
        "pop": 0,
        "sys": {
          "pod": "d"
        },
        "dt_txt": "2026-05-26 12:00:00"
      },
      {
        "dt": 1779807600,
        "main": {
          "temp": 41.88,
          "feels_like": 39.12,
          "temp_min": 41.88,
          "temp_max": 41.88,
          "pressure": 998,
          "sea_level": 998,
          "grnd_level": 974,
          "humidity": 11,
          "temp_kf": 0
        },
        "weather": [
          {
            "id": 801,
            "main": "Clouds",
            "description": "few clouds",
            "icon": "02n"
          }
        ],
        "clouds": {
          "all": 23
        },
        "wind": {
          "speed": 4.8,
          "deg": 311,
          "gust": 9.27
        },
        "visibility": 10000,
        "pop": 0,
        "sys": {
          "pod": "n"
        },
        "dt_txt": "2026-05-26 15:00:00"
      },
      {
        "dt": 1779818400,
        "main": {
          "temp": 39.49,
          "feels_like": 36.82,
          "temp_min": 39.49,
          "temp_max": 39.49,
          "pressure": 998,
          "sea_level": 998,
          "grnd_level": 974,
          "humidity": 12,
          "temp_kf": 0
        },
        "weather": [
          {
            "id": 800,
            "main": "Clear",
            "description": "clear sky",
            "icon": "01n"
          }
        ],
        "clouds": {
          "all": 10
        },
        "wind": {
          "speed": 3.64,
          "deg": 302,
          "gust": 9.17
        },
        "visibility": 10000,
        "pop": 0,
        "sys": {
          "pod": "n"
        },
        "dt_txt": "2026-05-26 18:00:00"
      },
      {
        "dt": 1779829200,
        "main": {
          "temp": 36.07,
          "feels_like": 33.22,
          "temp_min": 36.07,
          "temp_max": 36.07,
          "pressure": 998,
          "sea_level": 998,
          "grnd_level": 974,
          "humidity": 8,
          "temp_kf": 0
        },
        "weather": [
          {
            "id": 800,
            "main": "Clear",
            "description": "clear sky",
            "icon": "01n"
          }
        ],
        "clouds": {
          "all": 0
        },
        "wind": {
          "speed": 2.72,
          "deg": 329,
          "gust": 6.29
        },
        "visibility": 10000,
        "pop": 0,
        "sys": {
          "pod": "n"
        },
        "dt_txt": "2026-05-26 21:00:00"
      },
      {
        "dt": 1779840000,
        "main": {
          "temp": 34.39,
          "feels_like": 31.78,
          "temp_min": 34.39,
          "temp_max": 34.39,
          "pressure": 999,
          "sea_level": 999,
          "grnd_level": 975,
          "humidity": 8,
          "temp_kf": 0
        },
        "weather": [
          {
            "id": 800,
            "main": "Clear",
            "description": "clear sky",
            "icon": "01d"
          }
        ],
        "clouds": {
          "all": 0
        },
        "wind": {
          "speed": 2.05,
          "deg": 282,
          "gust": 2.92
        },
        "visibility": 10000,
        "pop": 0,
        "sys": {
          "pod": "d"
        },
        "dt_txt": "2026-05-27 00:00:00"
      },
      {
        "dt": 1779850800,
        "main": {
          "temp": 38.36,
          "feels_like": 35.13,
          "temp_min": 38.36,
          "temp_max": 38.36,
          "pressure": 1002,
          "sea_level": 1002,
          "grnd_level": 978,
          "humidity": 7,
          "temp_kf": 0
        },
        "weather": [
          {
            "id": 800,
            "main": "Clear",
            "description": "clear sky",
            "icon": "01d"
          }
        ],
        "clouds": {
          "all": 0
        },
        "wind": {
          "speed": 2.22,
          "deg": 303,
          "gust": 2.86
        },
        "visibility": 10000,
        "pop": 0,
        "sys": {
          "pod": "d"
        },
        "dt_txt": "2026-05-27 03:00:00"
      },
      {
        "dt": 1779861600,
        "main": {
          "temp": 42.98,
          "feels_like": 38.89,
          "temp_min": 42.98,
          "temp_max": 42.98,
          "pressure": 1002,
          "sea_level": 1002,
          "grnd_level": 978,
          "humidity": 6,
          "temp_kf": 0
        },
        "weather": [
          {
            "id": 800,
            "main": "Clear",
            "description": "clear sky",
            "icon": "01d"
          }
        ],
        "clouds": {
          "all": 0
        },
        "wind": {
          "speed": 2.94,
          "deg": 267,
          "gust": 5.04
        },
        "visibility": 10000,
        "pop": 0,
        "sys": {
          "pod": "d"
        },
        "dt_txt": "2026-05-27 06:00:00"
      },
      {
        "dt": 1779872400,
        "main": {
          "temp": 46.27,
          "feels_like": 41.23,
          "temp_min": 46.27,
          "temp_max": 46.27,
          "pressure": 998,
          "sea_level": 998,
          "grnd_level": 975,
          "humidity": 5,
          "temp_kf": 0
        },
        "weather": [
          {
            "id": 800,
            "main": "Clear",
            "description": "clear sky",
            "icon": "01d"
          }
        ],
        "clouds": {
          "all": 0
        },
        "wind": {
          "speed": 5.11,
          "deg": 291,
          "gust": 8.74
        },
        "visibility": 10000,
        "pop": 0,
        "sys": {
          "pod": "d"
        },
        "dt_txt": "2026-05-27 09:00:00"
      },
      {
        "dt": 1779883200,
        "main": {
          "temp": 46.26,
          "feels_like": 40.82,
          "temp_min": 46.26,
          "temp_max": 46.26,
          "pressure": 997,
          "sea_level": 997,
          "grnd_level": 973,
          "humidity": 4,
          "temp_kf": 0
        },
        "weather": [
          {
            "id": 800,
            "main": "Clear",
            "description": "clear sky",
            "icon": "01d"
          }
        ],
        "clouds": {
          "all": 0
        },
        "wind": {
          "speed": 5.64,
          "deg": 301,
          "gust": 8.52
        },
        "visibility": 10000,
        "pop": 0,
        "sys": {
          "pod": "d"
        },
        "dt_txt": "2026-05-27 12:00:00"
      },
      {
        "dt": 1779894000,
        "main": {
          "temp": 42.07,
          "feels_like": 37.95,
          "temp_min": 42.07,
          "temp_max": 42.07,
          "pressure": 998,
          "sea_level": 998,
          "grnd_level": 974,
          "humidity": 5,
          "temp_kf": 0
        },
        "weather": [
          {
            "id": 800,
            "main": "Clear",
            "description": "clear sky",
            "icon": "01n"
          }
        ],
        "clouds": {
          "all": 0
        },
        "wind": {
          "speed": 1.8,
          "deg": 303,
          "gust": 1.88
        },
        "visibility": 10000,
        "pop": 0,
        "sys": {
          "pod": "n"
        },
        "dt_txt": "2026-05-27 15:00:00"
      },
      {
        "dt": 1779904800,
        "main": {
          "temp": 39.89,
          "feels_like": 36.33,
          "temp_min": 39.89,
          "temp_max": 39.89,
          "pressure": 998,
          "sea_level": 998,
          "grnd_level": 974,
          "humidity": 6,
          "temp_kf": 0
        },
        "weather": [
          {
            "id": 800,
            "main": "Clear",
            "description": "clear sky",
            "icon": "01n"
          }
        ],
        "clouds": {
          "all": 0
        },
        "wind": {
          "speed": 1.45,
          "deg": 273,
          "gust": 1.92
        },
        "visibility": 10000,
        "pop": 0,
        "sys": {
          "pod": "n"
        },
        "dt_txt": "2026-05-27 18:00:00"
      },
      {
        "dt": 1779915600,
        "main": {
          "temp": 37.83,
          "feels_like": 35.01,
          "temp_min": 37.83,
          "temp_max": 37.83,
          "pressure": 997,
          "sea_level": 997,
          "grnd_level": 973,
          "humidity": 11,
          "temp_kf": 0
        },
        "weather": [
          {
            "id": 800,
            "main": "Clear",
            "description": "clear sky",
            "icon": "01n"
          }
        ],
        "clouds": {
          "all": 0
        },
        "wind": {
          "speed": 1.78,
          "deg": 237,
          "gust": 3.19
        },
        "visibility": 10000,
        "pop": 0,
        "sys": {
          "pod": "n"
        },
        "dt_txt": "2026-05-27 21:00:00"
      },
      {
        "dt": 1779926400,
        "main": {
          "temp": 35.19,
          "feels_like": 32.63,
          "temp_min": 35.19,
          "temp_max": 35.19,
          "pressure": 999,
          "sea_level": 999,
          "grnd_level": 975,
          "humidity": 13,
          "temp_kf": 0
        },
        "weather": [
          {
            "id": 800,
            "main": "Clear",
            "description": "clear sky",
            "icon": "01d"
          }
        ],
        "clouds": {
          "all": 0
        },
        "wind": {
          "speed": 2.43,
          "deg": 315,
          "gust": 6.42
        },
        "visibility": 10000,
        "pop": 0,
        "sys": {
          "pod": "d"
        },
        "dt_txt": "2026-05-28 00:00:00"
      },
      {
        "dt": 1779937200,
        "main": {
          "temp": 36.34,
          "feels_like": 34.04,
          "temp_min": 36.34,
          "temp_max": 36.34,
          "pressure": 1001,
          "sea_level": 1001,
          "grnd_level": 977,
          "humidity": 16,
          "temp_kf": 0
        },
        "weather": [
          {
            "id": 800,
            "main": "Clear",
            "description": "clear sky",
            "icon": "01d"
          }
        ],
        "clouds": {
          "all": 4
        },
        "wind": {
          "speed": 4.17,
          "deg": 108,
          "gust": 3.07
        },
        "visibility": 10000,
        "pop": 0,
        "sys": {
          "pod": "d"
        },
        "dt_txt": "2026-05-28 03:00:00"
      },
      {
        "dt": 1779948000,
        "main": {
          "temp": 42.07,
          "feels_like": 39.91,
          "temp_min": 42.07,
          "temp_max": 42.07,
          "pressure": 1000,
          "sea_level": 1000,
          "grnd_level": 976,
          "humidity": 13,
          "temp_kf": 0
        },
        "weather": [
          {
            "id": 800,
            "main": "Clear",
            "description": "clear sky",
            "icon": "01d"
          }
        ],
        "clouds": {
          "all": 2
        },
        "wind": {
          "speed": 2.03,
          "deg": 141,
          "gust": 1.35
        },
        "visibility": 10000,
        "pop": 0,
        "sys": {
          "pod": "d"
        },
        "dt_txt": "2026-05-28 06:00:00"
      },
      {
        "dt": 1779958800,
        "main": {
          "temp": 45.36,
          "feels_like": 42.07,
          "temp_min": 45.36,
          "temp_max": 45.36,
          "pressure": 998,
          "sea_level": 998,
          "grnd_level": 974,
          "humidity": 9,
          "temp_kf": 0
        },
        "weather": [
          {
            "id": 800,
            "main": "Clear",
            "description": "clear sky",
            "icon": "01d"
          }
        ],
        "clouds": {
          "all": 0
        },
        "wind": {
          "speed": 2.43,
          "deg": 248,
          "gust": 3.36
        },
        "visibility": 10000,
        "pop": 0,
        "sys": {
          "pod": "d"
        },
        "dt_txt": "2026-05-28 09:00:00"
      },
      {
        "dt": 1779969600,
        "main": {
          "temp": 46.35,
          "feels_like": 42.61,
          "temp_min": 46.35,
          "temp_max": 46.35,
          "pressure": 994,
          "sea_level": 994,
          "grnd_level": 971,
          "humidity": 8,
          "temp_kf": 0
        },
        "weather": [
          {
            "id": 800,
            "main": "Clear",
            "description": "clear sky",
            "icon": "01d"
          }
        ],
        "clouds": {
          "all": 0
        },
        "wind": {
          "speed": 1.07,
          "deg": 156,
          "gust": 4.45
        },
        "visibility": 10000,
        "pop": 0,
        "sys": {
          "pod": "d"
        },
        "dt_txt": "2026-05-28 12:00:00"
      },
      {
        "dt": 1779980400,
        "main": {
          "temp": 45.12,
          "feels_like": 41.05,
          "temp_min": 45.12,
          "temp_max": 45.12,
          "pressure": 995,
          "sea_level": 995,
          "grnd_level": 971,
          "humidity": 7,
          "temp_kf": 0
        },
        "weather": [
          {
            "id": 802,
            "main": "Clouds",
            "description": "scattered clouds",
            "icon": "03n"
          }
        ],
        "clouds": {
          "all": 26
        },
        "wind": {
          "speed": 6.34,
          "deg": 260,
          "gust": 12.05
        },
        "visibility": 10000,
        "pop": 0,
        "sys": {
          "pod": "n"
        },
        "dt_txt": "2026-05-28 15:00:00"
      },
      {
        "dt": 1779991200,
        "main": {
          "temp": 41.4,
          "feels_like": 38.38,
          "temp_min": 41.4,
          "temp_max": 41.4,
          "pressure": 997,
          "sea_level": 997,
          "grnd_level": 973,
          "humidity": 10,
          "temp_kf": 0
        },
        "weather": [
          {
            "id": 801,
            "main": "Clouds",
            "description": "few clouds",
            "icon": "02n"
          }
        ],
        "clouds": {
          "all": 13
        },
        "wind": {
          "speed": 4.79,
          "deg": 236,
          "gust": 9.97
        },
        "visibility": 10000,
        "pop": 0,
        "sys": {
          "pod": "n"
        },
        "dt_txt": "2026-05-28 18:00:00"
      },
      {
        "dt": 1780002000,
        "main": {
          "temp": 34.88,
          "feels_like": 34.71,
          "temp_min": 34.88,
          "temp_max": 34.88,
          "pressure": 999,
          "sea_level": 999,
          "grnd_level": 975,
          "humidity": 31,
          "temp_kf": 0
        },
        "weather": [
          {
            "id": 802,
            "main": "Clouds",
            "description": "scattered clouds",
            "icon": "03n"
          }
        ],
        "clouds": {
          "all": 31
        },
        "wind": {
          "speed": 7.19,
          "deg": 115,
          "gust": 8.96
        },
        "visibility": 10000,
        "pop": 0,
        "sys": {
          "pod": "n"
        },
        "dt_txt": "2026-05-28 21:00:00"
      },
      {
        "dt": 1780012800,
        "main": {
          "temp": 32.28,
          "feels_like": 32.88,
          "temp_min": 32.28,
          "temp_max": 32.28,
          "pressure": 1000,
          "sea_level": 1000,
          "grnd_level": 976,
          "humidity": 41,
          "temp_kf": 0
        },
        "weather": [
          {
            "id": 802,
            "main": "Clouds",
            "description": "scattered clouds",
            "icon": "03d"
          }
        ],
        "clouds": {
          "all": 29
        },
        "wind": {
          "speed": 6.26,
          "deg": 126,
          "gust": 10.81
        },
        "visibility": 10000,
        "pop": 0,
        "sys": {
          "pod": "d"
        },
        "dt_txt": "2026-05-29 00:00:00"
      },
      {
        "dt": 1780023600,
        "main": {
          "temp": 34.61,
          "feels_like": 35.44,
          "temp_min": 34.61,
          "temp_max": 34.61,
          "pressure": 1002,
          "sea_level": 1002,
          "grnd_level": 978,
          "humidity": 36,
          "temp_kf": 0
        },
        "weather": [
          {
            "id": 800,
            "main": "Clear",
            "description": "clear sky",
            "icon": "01d"
          }
        ],
        "clouds": {
          "all": 2
        },
        "wind": {
          "speed": 7.66,
          "deg": 122,
          "gust": 9.48
        },
        "visibility": 10000,
        "pop": 0,
        "sys": {
          "pod": "d"
        },
        "dt_txt": "2026-05-29 03:00:00"
      },
      {
        "dt": 1780034400,
        "main": {
          "temp": 40.01,
          "feels_like": 41.48,
          "temp_min": 40.01,
          "temp_max": 40.01,
          "pressure": 1001,
          "sea_level": 1001,
          "grnd_level": 977,
          "humidity": 26,
          "temp_kf": 0
        },
        "weather": [
          {
            "id": 801,
            "main": "Clouds",
            "description": "few clouds",
            "icon": "02d"
          }
        ],
        "clouds": {
          "all": 13
        },
        "wind": {
          "speed": 6.01,
          "deg": 133,
          "gust": 6.4
        },
        "visibility": 10000,
        "pop": 0,
        "sys": {
          "pod": "d"
        },
        "dt_txt": "2026-05-29 06:00:00"
      },
      {
        "dt": 1780045200,
        "main": {
          "temp": 44.02,
          "feels_like": 43.57,
          "temp_min": 44.02,
          "temp_max": 44.02,
          "pressure": 997,
          "sea_level": 997,
          "grnd_level": 973,
          "humidity": 16,
          "temp_kf": 0
        },
        "weather": [
          {
            "id": 800,
            "main": "Clear",
            "description": "clear sky",
            "icon": "01d"
          }
        ],
        "clouds": {
          "all": 1
        },
        "wind": {
          "speed": 3.62,
          "deg": 113,
          "gust": 6.33
        },
        "visibility": 10000,
        "pop": 0,
        "sys": {
          "pod": "d"
        },
        "dt_txt": "2026-05-29 09:00:00"
      },
      {
        "dt": 1780056000,
        "main": {
          "temp": 45.13,
          "feels_like": 42.26,
          "temp_min": 45.13,
          "temp_max": 45.13,
          "pressure": 994,
          "sea_level": 994,
          "grnd_level": 970,
          "humidity": 10,
          "temp_kf": 0
        },
        "weather": [
          {
            "id": 800,
            "main": "Clear",
            "description": "clear sky",
            "icon": "01d"
          }
        ],
        "clouds": {
          "all": 0
        },
        "wind": {
          "speed": 4.33,
          "deg": 226,
          "gust": 5.72
        },
        "visibility": 10000,
        "pop": 0,
        "sys": {
          "pod": "d"
        },
        "dt_txt": "2026-05-29 12:00:00"
      },
      {
        "dt": 1780066800,
        "main": {
          "temp": 43.13,
          "feels_like": 39.02,
          "temp_min": 43.13,
          "temp_max": 43.13,
          "pressure": 994,
          "sea_level": 994,
          "grnd_level": 971,
          "humidity": 6,
          "temp_kf": 0
        },
        "weather": [
          {
            "id": 800,
            "main": "Clear",
            "description": "clear sky",
            "icon": "01n"
          }
        ],
        "clouds": {
          "all": 0
        },
        "wind": {
          "speed": 4.45,
          "deg": 272,
          "gust": 7.11
        },
        "visibility": 10000,
        "pop": 0,
        "sys": {
          "pod": "n"
        },
        "dt_txt": "2026-05-29 15:00:00"
      },
      {
        "dt": 1780077600,
        "main": {
          "temp": 30.52,
          "feels_like": 31.17,
          "temp_min": 30.52,
          "temp_max": 30.52,
          "pressure": 1000,
          "sea_level": 1000,
          "grnd_level": 976,
          "humidity": 46,
          "temp_kf": 0
        },
        "weather": [
          {
            "id": 802,
            "main": "Clouds",
            "description": "scattered clouds",
            "icon": "03n"
          }
        ],
        "clouds": {
          "all": 48
        },
        "wind": {
          "speed": 8.72,
          "deg": 66,
          "gust": 12.12
        },
        "visibility": 10000,
        "pop": 0,
        "sys": {
          "pod": "n"
        },
        "dt_txt": "2026-05-29 18:00:00"
      },
      {
        "dt": 1780088400,
        "main": {
          "temp": 28.28,
          "feels_like": 28.87,
          "temp_min": 28.28,
          "temp_max": 28.28,
          "pressure": 1000,
          "sea_level": 1000,
          "grnd_level": 975,
          "humidity": 51,
          "temp_kf": 0
        },
        "weather": [
          {
            "id": 804,
            "main": "Clouds",
            "description": "overcast clouds",
            "icon": "04n"
          }
        ],
        "clouds": {
          "all": 100
        },
        "wind": {
          "speed": 7.47,
          "deg": 140,
          "gust": 14.59
        },
        "visibility": 10000,
        "pop": 0,
        "sys": {
          "pod": "n"
        },
        "dt_txt": "2026-05-29 21:00:00"
      },
      {
        "dt": 1780099200,
        "main": {
          "temp": 27.84,
          "feels_like": 28.63,
          "temp_min": 27.84,
          "temp_max": 27.84,
          "pressure": 1001,
          "sea_level": 1001,
          "grnd_level": 977,
          "humidity": 54,
          "temp_kf": 0
        },
        "weather": [
          {
            "id": 500,
            "main": "Rain",
            "description": "light rain",
            "icon": "10d"
          }
        ],
        "clouds": {
          "all": 96
        },
        "wind": {
          "speed": 6.02,
          "deg": 149,
          "gust": 12.8
        },
        "visibility": 10000,
        "pop": 0.2,
        "rain": {
          "3h": 0.21
        },
        "sys": {
          "pod": "d"
        },
        "dt_txt": "2026-05-30 00:00:00"
      },
      {
        "dt": 1780110000,
        "main": {
          "temp": 31.1,
          "feels_like": 31.35,
          "temp_min": 31.1,
          "temp_max": 31.1,
          "pressure": 1003,
          "sea_level": 1003,
          "grnd_level": 979,
          "humidity": 42,
          "temp_kf": 0
        },
        "weather": [
          {
            "id": 803,
            "main": "Clouds",
            "description": "broken clouds",
            "icon": "04d"
          }
        ],
        "clouds": {
          "all": 59
        },
        "wind": {
          "speed": 7.45,
          "deg": 120,
          "gust": 10.15
        },
        "visibility": 10000,
        "pop": 0,
        "sys": {
          "pod": "d"
        },
        "dt_txt": "2026-05-30 03:00:00"
      },
      {
        "dt": 1780120800,
        "main": {
          "temp": 36.76,
          "feels_like": 37.36,
          "temp_min": 36.76,
          "temp_max": 36.76,
          "pressure": 1002,
          "sea_level": 1002,
          "grnd_level": 978,
          "humidity": 30,
          "temp_kf": 0
        },
        "weather": [
          {
            "id": 803,
            "main": "Clouds",
            "description": "broken clouds",
            "icon": "04d"
          }
        ],
        "clouds": {
          "all": 57
        },
        "wind": {
          "speed": 6.75,
          "deg": 126,
          "gust": 8.13
        },
        "visibility": 10000,
        "pop": 0,
        "sys": {
          "pod": "d"
        },
        "dt_txt": "2026-05-30 06:00:00"
      },
      {
        "dt": 1780131600,
        "main": {
          "temp": 40.57,
          "feels_like": 41.65,
          "temp_min": 40.57,
          "temp_max": 40.57,
          "pressure": 999,
          "sea_level": 999,
          "grnd_level": 976,
          "humidity": 24,
          "temp_kf": 0
        },
        "weather": [
          {
            "id": 800,
            "main": "Clear",
            "description": "clear sky",
            "icon": "01d"
          }
        ],
        "clouds": {
          "all": 0
        },
        "wind": {
          "speed": 5.18,
          "deg": 123,
          "gust": 6.08
        },
        "visibility": 10000,
        "pop": 0,
        "sys": {
          "pod": "d"
        },
        "dt_txt": "2026-05-30 09:00:00"
      },
      {
        "dt": 1780142400,
        "main": {
          "temp": 40.86,
          "feels_like": 41.35,
          "temp_min": 40.86,
          "temp_max": 40.86,
          "pressure": 996,
          "sea_level": 996,
          "grnd_level": 972,
          "humidity": 22,
          "temp_kf": 0
        },
        "weather": [
          {
            "id": 801,
            "main": "Clouds",
            "description": "few clouds",
            "icon": "02d"
          }
        ],
        "clouds": {
          "all": 19
        },
        "wind": {
          "speed": 3.73,
          "deg": 83,
          "gust": 3.36
        },
        "visibility": 10000,
        "pop": 0,
        "sys": {
          "pod": "d"
        },
        "dt_txt": "2026-05-30 12:00:00"
      },
      {
        "dt": 1780153200,
        "main": {
          "temp": 29.56,
          "feels_like": 29.41,
          "temp_min": 29.56,
          "temp_max": 29.56,
          "pressure": 999,
          "sea_level": 999,
          "grnd_level": 975,
          "humidity": 42,
          "temp_kf": 0
        },
        "weather": [
          {
            "id": 500,
            "main": "Rain",
            "description": "light rain",
            "icon": "10n"
          }
        ],
        "clouds": {
          "all": 66
        },
        "wind": {
          "speed": 7.26,
          "deg": 196,
          "gust": 13.62
        },
        "visibility": 10000,
        "pop": 1,
        "rain": {
          "3h": 1.56
        },
        "sys": {
          "pod": "n"
        },
        "dt_txt": "2026-05-30 15:00:00"
      }
    ],
    "city": {
      "id": 1271308,
      "name": "Ghaziabad",
      "coord": {
        "lat": 28.6692,
        "lon": 77.438
      },
      "country": "IN",
      "population": 1199191,
      "timezone": 19800,
      "sunrise": 1779666897,
      "sunset": 1779716380
    }
  },
  "tomorrow": {
    "data": {
      "time": "2026-05-25T17:22:00Z",
      "values": {
        "altimeterSetting": 1002.21,
        "cloudBase": null,
        "cloudCeiling": null,
        "cloudCover": 0,
        "dewPoint": 25.3,
        "freezingRainIntensity": 0,
        "humidity": 62,
        "precipitationProbability": 0,
        "pressureSeaLevel": 998.06,
        "pressureSurfaceLevel": 977.96,
        "rainIntensity": 0,
        "sleetIntensity": 0,
        "snowIntensity": 0,
        "temperature": 32.06,
        "temperatureApparent": 37.8,
        "uvHealthConcern": 0,
        "uvIndex": 0,
        "visibility": 11.6,
        "weatherCode": 1000,
        "windDirection": 51,
        "windGust": 1.3,
        "windSpeed": 0
      }
    },
    "location": {
      "lat": 28.6692,
      "lon": 77.438
    }
  }
}