{
  "lastUpdated": "2026-02-27T22:56:09Z",
  "lastUpdatedIST": "2026-02-28 04:26:09 IST",
  "timestamp": 1772232969,
  "refreshInterval": "5 minutes",
  "source": "GitHub Actions",
  "openweather": {
    "coord": {
      "lon": 77.438,
      "lat": 28.6692
    },
    "weather": [
      {
        "id": 800,
        "main": "Clear",
        "description": "clear sky",
        "icon": "01n"
      }
    ],
    "base": "stations",
    "main": {
      "temp": 19.47,
      "feels_like": 18.07,
      "temp_min": 19.47,
      "temp_max": 19.47,
      "pressure": 1006,
      "humidity": 23,
      "sea_level": 1006,
      "grnd_level": 982
    },
    "visibility": 10000,
    "wind": {
      "speed": 2.23,
      "deg": 283,
      "gust": 3.04
    },
    "clouds": {
      "all": 3
    },
    "dt": 1772232969,
    "sys": {
      "country": "IN",
      "sunrise": 1772241420,
      "sunset": 1772282944
    },
    "timezone": 19800,
    "id": 1271308,
    "name": "Ghaziabad",
    "cod": 200
  },
  "airPollution": {
    "coord": {
      "lon": 77.438,
      "lat": 28.6692
    },
    "list": [
      {
        "main": {
          "aqi": 4
        },
        "components": {
          "co": 575.16,
          "no": 0,
          "no2": 15.35,
          "o3": 27.06,
          "so2": 1.59,
          "pm2_5": 74.69,
          "pm10": 113.51,
          "nh3": 31.91
        },
        "dt": 1772232969
      }
    ]
  },
  "forecast": {
    "cod": "200",
    "message": 0,
    "cnt": 40,
    "list": [
      {
        "dt": 1772236800,
        "main": {
          "temp": 19.17,
          "feels_like": 17.74,
          "temp_min": 19.17,
          "temp_max": 19.17,
          "pressure": 1007,
          "sea_level": 1007,
          "grnd_level": 982,
          "humidity": 23,
          "temp_kf": 0
        },
        "weather": [
          {
            "id": 800,
            "main": "Clear",
            "description": "clear sky",
            "icon": "01n"
          }
        ],
        "clouds": {
          "all": 5
        },
        "wind": {
          "speed": 2.04,
          "deg": 316,
          "gust": 2.14
        },
        "visibility": 10000,
        "pop": 0,
        "sys": {
          "pod": "n"
        },
        "dt_txt": "2026-02-28 00:00:00"
      },
      {
        "dt": 1772247600,
        "main": {
          "temp": 20.13,
          "feels_like": 18.77,
          "temp_min": 20.13,
          "temp_max": 22.05,
          "pressure": 1008,
          "sea_level": 1008,
          "grnd_level": 984,
          "humidity": 22,
          "temp_kf": -1.92
        },
        "weather": [
          {
            "id": 800,
            "main": "Clear",
            "description": "clear sky",
            "icon": "01d"
          }
        ],
        "clouds": {
          "all": 3
        },
        "wind": {
          "speed": 1.36,
          "deg": 282,
          "gust": 1.95
        },
        "visibility": 10000,
        "pop": 0,
        "sys": {
          "pod": "d"
        },
        "dt_txt": "2026-02-28 03:00:00"
      },
      {
        "dt": 1772258400,
        "main": {
          "temp": 26.38,
          "feels_like": 26.38,
          "temp_min": 26.38,
          "temp_max": 29.99,
          "pressure": 1008,
          "sea_level": 1008,
          "grnd_level": 984,
          "humidity": 17,
          "temp_kf": -3.61
        },
        "weather": [
          {
            "id": 800,
            "main": "Clear",
            "description": "clear sky",
            "icon": "01d"
          }
        ],
        "clouds": {
          "all": 2
        },
        "wind": {
          "speed": 3.17,
          "deg": 265,
          "gust": 3.99
        },
        "visibility": 10000,
        "pop": 0,
        "sys": {
          "pod": "d"
        },
        "dt_txt": "2026-02-28 06:00:00"
      },
      {
        "dt": 1772269200,
        "main": {
          "temp": 32.69,
          "feels_like": 30.36,
          "temp_min": 32.69,
          "temp_max": 32.69,
          "pressure": 1005,
          "sea_level": 1005,
          "grnd_level": 981,
          "humidity": 13,
          "temp_kf": 0
        },
        "weather": [
          {
            "id": 800,
            "main": "Clear",
            "description": "clear sky",
            "icon": "01d"
          }
        ],
        "clouds": {
          "all": 0
        },
        "wind": {
          "speed": 4.64,
          "deg": 281,
          "gust": 6.8
        },
        "visibility": 10000,
        "pop": 0,
        "sys": {
          "pod": "d"
        },
        "dt_txt": "2026-02-28 09:00:00"
      },
      {
        "dt": 1772280000,
        "main": {
          "temp": 30.89,
          "feels_like": 28.85,
          "temp_min": 30.89,
          "temp_max": 30.89,
          "pressure": 1004,
          "sea_level": 1004,
          "grnd_level": 980,
          "humidity": 14,
          "temp_kf": 0
        },
        "weather": [
          {
            "id": 800,
            "main": "Clear",
            "description": "clear sky",
            "icon": "01d"
          }
        ],
        "clouds": {
          "all": 2
        },
        "wind": {
          "speed": 4.08,
          "deg": 272,
          "gust": 6.76
        },
        "visibility": 10000,
        "pop": 0,
        "sys": {
          "pod": "d"
        },
        "dt_txt": "2026-02-28 12:00:00"
      },
      {
        "dt": 1772290800,
        "main": {
          "temp": 25.75,
          "feels_like": 24.88,
          "temp_min": 25.75,
          "temp_max": 25.75,
          "pressure": 1006,
          "sea_level": 1006,
          "grnd_level": 982,
          "humidity": 19,
          "temp_kf": 0
        },
        "weather": [
          {
            "id": 800,
            "main": "Clear",
            "description": "clear sky",
            "icon": "01n"
          }
        ],
        "clouds": {
          "all": 2
        },
        "wind": {
          "speed": 2.95,
          "deg": 289,
          "gust": 7.03
        },
        "visibility": 10000,
        "pop": 0,
        "sys": {
          "pod": "n"
        },
        "dt_txt": "2026-02-28 15:00:00"
      },
      {
        "dt": 1772301600,
        "main": {
          "temp": 22.68,
          "feels_like": 21.6,
          "temp_min": 22.68,
          "temp_max": 22.68,
          "pressure": 1007,
          "sea_level": 1007,
          "grnd_level": 982,
          "humidity": 23,
          "temp_kf": 0
        },
        "weather": [
          {
            "id": 800,
            "main": "Clear",
            "description": "clear sky",
            "icon": "01n"
          }
        ],
        "clouds": {
          "all": 1
        },
        "wind": {
          "speed": 2.67,
          "deg": 306,
          "gust": 4.71
        },
        "visibility": 10000,
        "pop": 0,
        "sys": {
          "pod": "n"
        },
        "dt_txt": "2026-02-28 18:00:00"
      },
      {
        "dt": 1772312400,
        "main": {
          "temp": 21.06,
          "feels_like": 19.8,
          "temp_min": 21.06,
          "temp_max": 21.06,
          "pressure": 1006,
          "sea_level": 1006,
          "grnd_level": 982,
          "humidity": 22,
          "temp_kf": 0
        },
        "weather": [
          {
            "id": 800,
            "main": "Clear",
            "description": "clear sky",
            "icon": "01n"
          }
        ],
        "clouds": {
          "all": 0
        },
        "wind": {
          "speed": 2.37,
          "deg": 318,
          "gust": 2.96
        },
        "visibility": 10000,
        "pop": 0,
        "sys": {
          "pod": "n"
        },
        "dt_txt": "2026-02-28 21:00:00"
      },
      {
        "dt": 1772323200,
        "main": {
          "temp": 20.21,
          "feels_like": 18.83,
          "temp_min": 20.21,
          "temp_max": 20.21,
          "pressure": 1006,
          "sea_level": 1006,
          "grnd_level": 982,
          "humidity": 21,
          "temp_kf": 0
        },
        "weather": [
          {
            "id": 800,
            "main": "Clear",
            "description": "clear sky",
            "icon": "01n"
          }
        ],
        "clouds": {
          "all": 0
        },
        "wind": {
          "speed": 2.41,
          "deg": 301,
          "gust": 2.55
        },
        "visibility": 10000,
        "pop": 0,
        "sys": {
          "pod": "n"
        },
        "dt_txt": "2026-03-01 00:00:00"
      },
      {
        "dt": 1772334000,
        "main": {
          "temp": 22.89,
          "feels_like": 21.7,
          "temp_min": 22.89,
          "temp_max": 22.89,
          "pressure": 1009,
          "sea_level": 1009,
          "grnd_level": 984,
          "humidity": 18,
          "temp_kf": 0
        },
        "weather": [
          {
            "id": 800,
            "main": "Clear",
            "description": "clear sky",
            "icon": "01d"
          }
        ],
        "clouds": {
          "all": 0
        },
        "wind": {
          "speed": 2.93,
          "deg": 302,
          "gust": 5.06
        },
        "visibility": 10000,
        "pop": 0,
        "sys": {
          "pod": "d"
        },
        "dt_txt": "2026-03-01 03:00:00"
      },
      {
        "dt": 1772344800,
        "main": {
          "temp": 31.09,
          "feels_like": 29.02,
          "temp_min": 31.09,
          "temp_max": 31.09,
          "pressure": 1009,
          "sea_level": 1009,
          "grnd_level": 985,
          "humidity": 10,
          "temp_kf": 0
        },
        "weather": [
          {
            "id": 800,
            "main": "Clear",
            "description": "clear sky",
            "icon": "01d"
          }
        ],
        "clouds": {
          "all": 0
        },
        "wind": {
          "speed": 3.68,
          "deg": 288,
          "gust": 7.09
        },
        "visibility": 10000,
        "pop": 0,
        "sys": {
          "pod": "d"
        },
        "dt_txt": "2026-03-01 06:00:00"
      },
      {
        "dt": 1772355600,
        "main": {
          "temp": 33.6,
          "feels_like": 31.12,
          "temp_min": 33.6,
          "temp_max": 33.6,
          "pressure": 1006,
          "sea_level": 1006,
          "grnd_level": 982,
          "humidity": 8,
          "temp_kf": 0
        },
        "weather": [
          {
            "id": 800,
            "main": "Clear",
            "description": "clear sky",
            "icon": "01d"
          }
        ],
        "clouds": {
          "all": 0
        },
        "wind": {
          "speed": 6.11,
          "deg": 297,
          "gust": 8.38
        },
        "visibility": 10000,
        "pop": 0,
        "sys": {
          "pod": "d"
        },
        "dt_txt": "2026-03-01 09:00:00"
      },
      {
        "dt": 1772366400,
        "main": {
          "temp": 31.43,
          "feels_like": 29.33,
          "temp_min": 31.43,
          "temp_max": 31.43,
          "pressure": 1005,
          "sea_level": 1005,
          "grnd_level": 981,
          "humidity": 8,
          "temp_kf": 0
        },
        "weather": [
          {
            "id": 800,
            "main": "Clear",
            "description": "clear sky",
            "icon": "01d"
          }
        ],
        "clouds": {
          "all": 0
        },
        "wind": {
          "speed": 4.42,
          "deg": 319,
          "gust": 7.93
        },
        "visibility": 10000,
        "pop": 0,
        "sys": {
          "pod": "d"
        },
        "dt_txt": "2026-03-01 12:00:00"
      },
      {
        "dt": 1772377200,
        "main": {
          "temp": 25.85,
          "feels_like": 24.88,
          "temp_min": 25.85,
          "temp_max": 25.85,
          "pressure": 1008,
          "sea_level": 1008,
          "grnd_level": 983,
          "humidity": 15,
          "temp_kf": 0
        },
        "weather": [
          {
            "id": 800,
            "main": "Clear",
            "description": "clear sky",
            "icon": "01n"
          }
        ],
        "clouds": {
          "all": 1
        },
        "wind": {
          "speed": 3.48,
          "deg": 296,
          "gust": 9.22
        },
        "visibility": 10000,
        "pop": 0,
        "sys": {
          "pod": "n"
        },
        "dt_txt": "2026-03-01 15:00:00"
      },
      {
        "dt": 1772388000,
        "main": {
          "temp": 22.91,
          "feels_like": 21.67,
          "temp_min": 22.91,
          "temp_max": 22.91,
          "pressure": 1009,
          "sea_level": 1009,
          "grnd_level": 984,
          "humidity": 16,
          "temp_kf": 0
        },
        "weather": [
          {
            "id": 800,
            "main": "Clear",
            "description": "clear sky",
            "icon": "01n"
          }
        ],
        "clouds": {
          "all": 2
        },
        "wind": {
          "speed": 2.67,
          "deg": 311,
          "gust": 4.92
        },
        "visibility": 10000,
        "pop": 0,
        "sys": {
          "pod": "n"
        },
        "dt_txt": "2026-03-01 18:00:00"
      },
      {
        "dt": 1772398800,
        "main": {
          "temp": 21.18,
          "feels_like": 19.69,
          "temp_min": 21.18,
          "temp_max": 21.18,
          "pressure": 1008,
          "sea_level": 1008,
          "grnd_level": 983,
          "humidity": 13,
          "temp_kf": 0
        },
        "weather": [
          {
            "id": 800,
            "main": "Clear",
            "description": "clear sky",
            "icon": "01n"
          }
        ],
        "clouds": {
          "all": 6
        },
        "wind": {
          "speed": 2.6,
          "deg": 318,
          "gust": 4.19
        },
        "visibility": 10000,
        "pop": 0,
        "sys": {
          "pod": "n"
        },
        "dt_txt": "2026-03-01 21:00:00"
      },
      {
        "dt": 1772409600,
        "main": {
          "temp": 20.03,
          "feels_like": 18.4,
          "temp_min": 20.03,
          "temp_max": 20.03,
          "pressure": 1008,
          "sea_level": 1008,
          "grnd_level": 983,
          "humidity": 12,
          "temp_kf": 0
        },
        "weather": [
          {
            "id": 800,
            "main": "Clear",
            "description": "clear sky",
            "icon": "01n"
          }
        ],
        "clouds": {
          "all": 3
        },
        "wind": {
          "speed": 2.58,
          "deg": 294,
          "gust": 3.87
        },
        "visibility": 10000,
        "pop": 0,
        "sys": {
          "pod": "n"
        },
        "dt_txt": "2026-03-02 00:00:00"
      },
      {
        "dt": 1772420400,
        "main": {
          "temp": 23.08,
          "feels_like": 21.76,
          "temp_min": 23.08,
          "temp_max": 23.08,
          "pressure": 1011,
          "sea_level": 1011,
          "grnd_level": 986,
          "humidity": 12,
          "temp_kf": 0
        },
        "weather": [
          {
            "id": 800,
            "main": "Clear",
            "description": "clear sky",
            "icon": "01d"
          }
        ],
        "clouds": {
          "all": 0
        },
        "wind": {
          "speed": 3.56,
          "deg": 294,
          "gust": 6.43
        },
        "visibility": 10000,
        "pop": 0,
        "sys": {
          "pod": "d"
        },
        "dt_txt": "2026-03-02 03:00:00"
      },
      {
        "dt": 1772431200,
        "main": {
          "temp": 31.13,
          "feels_like": 29.09,
          "temp_min": 31.13,
          "temp_max": 31.13,
          "pressure": 1011,
          "sea_level": 1011,
          "grnd_level": 986,
          "humidity": 8,
          "temp_kf": 0
        },
        "weather": [
          {
            "id": 800,
            "main": "Clear",
            "description": "clear sky",
            "icon": "01d"
          }
        ],
        "clouds": {
          "all": 0
        },
        "wind": {
          "speed": 4.54,
          "deg": 277,
          "gust": 6.76
        },
        "visibility": 10000,
        "pop": 0,
        "sys": {
          "pod": "d"
        },
        "dt_txt": "2026-03-02 06:00:00"
      },
      {
        "dt": 1772442000,
        "main": {
          "temp": 34.47,
          "feels_like": 31.87,
          "temp_min": 34.47,
          "temp_max": 34.47,
          "pressure": 1008,
          "sea_level": 1008,
          "grnd_level": 983,
          "humidity": 6,
          "temp_kf": 0
        },
        "weather": [
          {
            "id": 800,
            "main": "Clear",
            "description": "clear sky",
            "icon": "01d"
          }
        ],
        "clouds": {
          "all": 0
        },
        "wind": {
          "speed": 6.66,
          "deg": 300,
          "gust": 9.48
        },
        "visibility": 10000,
        "pop": 0,
        "sys": {
          "pod": "d"
        },
        "dt_txt": "2026-03-02 09:00:00"
      },
      {
        "dt": 1772452800,
        "main": {
          "temp": 32.56,
          "feels_like": 30.26,
          "temp_min": 32.56,
          "temp_max": 32.56,
          "pressure": 1007,
          "sea_level": 1007,
          "grnd_level": 982,
          "humidity": 8,
          "temp_kf": 0
        },
        "weather": [
          {
            "id": 800,
            "main": "Clear",
            "description": "clear sky",
            "icon": "01d"
          }
        ],
        "clouds": {
          "all": 7
        },
        "wind": {
          "speed": 5.08,
          "deg": 306,
          "gust": 8.73
        },
        "visibility": 10000,
        "pop": 0,
        "sys": {
          "pod": "d"
        },
        "dt_txt": "2026-03-02 12:00:00"
      },
      {
        "dt": 1772463600,
        "main": {
          "temp": 27.02,
          "feels_like": 25.97,
          "temp_min": 27.02,
          "temp_max": 27.02,
          "pressure": 1009,
          "sea_level": 1009,
          "grnd_level": 985,
          "humidity": 15,
          "temp_kf": 0
        },
        "weather": [
          {
            "id": 800,
            "main": "Clear",
            "description": "clear sky",
            "icon": "01n"
          }
        ],
        "clouds": {
          "all": 0
        },
        "wind": {
          "speed": 4.49,
          "deg": 281,
          "gust": 11.35
        },
        "visibility": 10000,
        "pop": 0,
        "sys": {
          "pod": "n"
        },
        "dt_txt": "2026-03-02 15:00:00"
      },
      {
        "dt": 1772474400,
        "main": {
          "temp": 23.52,
          "feels_like": 22.35,
          "temp_min": 23.52,
          "temp_max": 23.52,
          "pressure": 1010,
          "sea_level": 1010,
          "grnd_level": 985,
          "humidity": 16,
          "temp_kf": 0
        },
        "weather": [
          {
            "id": 800,
            "main": "Clear",
            "description": "clear sky",
            "icon": "01n"
          }
        ],
        "clouds": {
          "all": 8
        },
        "wind": {
          "speed": 3.57,
          "deg": 305,
          "gust": 7.88
        },
        "visibility": 10000,
        "pop": 0,
        "sys": {
          "pod": "n"
        },
        "dt_txt": "2026-03-02 18:00:00"
      },
      {
        "dt": 1772485200,
        "main": {
          "temp": 21.01,
          "feels_like": 19.48,
          "temp_min": 21.01,
          "temp_max": 21.01,
          "pressure": 1009,
          "sea_level": 1009,
          "grnd_level": 984,
          "humidity": 12,
          "temp_kf": 0
        },
        "weather": [
          {
            "id": 803,
            "main": "Clouds",
            "description": "broken clouds",
            "icon": "04n"
          }
        ],
        "clouds": {
          "all": 71
        },
        "wind": {
          "speed": 3.29,
          "deg": 298,
          "gust": 7.92
        },
        "visibility": 10000,
        "pop": 0,
        "sys": {
          "pod": "n"
        },
        "dt_txt": "2026-03-02 21:00:00"
      },
      {
        "dt": 1772496000,
        "main": {
          "temp": 20,
          "feels_like": 18.37,
          "temp_min": 20,
          "temp_max": 20,
          "pressure": 1008,
          "sea_level": 1008,
          "grnd_level": 983,
          "humidity": 12,
          "temp_kf": 0
        },
        "weather": [
          {
            "id": 802,
            "main": "Clouds",
            "description": "scattered clouds",
            "icon": "03n"
          }
        ],
        "clouds": {
          "all": 39
        },
        "wind": {
          "speed": 3.78,
          "deg": 296,
          "gust": 10.54
        },
        "visibility": 10000,
        "pop": 0,
        "sys": {
          "pod": "n"
        },
        "dt_txt": "2026-03-03 00:00:00"
      },
      {
        "dt": 1772506800,
        "main": {
          "temp": 23.09,
          "feels_like": 21.74,
          "temp_min": 23.09,
          "temp_max": 23.09,
          "pressure": 1010,
          "sea_level": 1010,
          "grnd_level": 985,
          "humidity": 11,
          "temp_kf": 0
        },
        "weather": [
          {
            "id": 800,
            "main": "Clear",
            "description": "clear sky",
            "icon": "01d"
          }
        ],
        "clouds": {
          "all": 3
        },
        "wind": {
          "speed": 4.56,
          "deg": 299,
          "gust": 10.23
        },
        "visibility": 10000,
        "pop": 0,
        "sys": {
          "pod": "d"
        },
        "dt_txt": "2026-03-03 03:00:00"
      },
      {
        "dt": 1772517600,
        "main": {
          "temp": 31.81,
          "feels_like": 29.64,
          "temp_min": 31.81,
          "temp_max": 31.81,
          "pressure": 1010,
          "sea_level": 1010,
          "grnd_level": 985,
          "humidity": 8,
          "temp_kf": 0
        },
        "weather": [
          {
            "id": 800,
            "main": "Clear",
            "description": "clear sky",
            "icon": "01d"
          }
        ],
        "clouds": {
          "all": 2
        },
        "wind": {
          "speed": 6.35,
          "deg": 292,
          "gust": 10.01
        },
        "visibility": 10000,
        "pop": 0,
        "sys": {
          "pod": "d"
        },
        "dt_txt": "2026-03-03 06:00:00"
      },
      {
        "dt": 1772528400,
        "main": {
          "temp": 35.44,
          "feels_like": 32.67,
          "temp_min": 35.44,
          "temp_max": 35.44,
          "pressure": 1006,
          "sea_level": 1006,
          "grnd_level": 982,
          "humidity": 5,
          "temp_kf": 0
        },
        "weather": [
          {
            "id": 800,
            "main": "Clear",
            "description": "clear sky",
            "icon": "01d"
          }
        ],
        "clouds": {
          "all": 0
        },
        "wind": {
          "speed": 6.69,
          "deg": 296,
          "gust": 8.95
        },
        "visibility": 10000,
        "pop": 0,
        "sys": {
          "pod": "d"
        },
        "dt_txt": "2026-03-03 09:00:00"
      },
      {
        "dt": 1772539200,
        "main": {
          "temp": 33.55,
          "feels_like": 31.15,
          "temp_min": 33.55,
          "temp_max": 33.55,
          "pressure": 1006,
          "sea_level": 1006,
          "grnd_level": 982,
          "humidity": 5,
          "temp_kf": 0
        },
        "weather": [
          {
            "id": 800,
            "main": "Clear",
            "description": "clear sky",
            "icon": "01d"
          }
        ],
        "clouds": {
          "all": 0
        },
        "wind": {
          "speed": 4.88,
          "deg": 297,
          "gust": 8.81
        },
        "visibility": 10000,
        "pop": 0,
        "sys": {
          "pod": "d"
        },
        "dt_txt": "2026-03-03 12:00:00"
      },
      {
        "dt": 1772550000,
        "main": {
          "temp": 27.08,
          "feels_like": 25.91,
          "temp_min": 27.08,
          "temp_max": 27.08,
          "pressure": 1009,
          "sea_level": 1009,
          "grnd_level": 984,
          "humidity": 9,
          "temp_kf": 0
        },
        "weather": [
          {
            "id": 800,
            "main": "Clear",
            "description": "clear sky",
            "icon": "01n"
          }
        ],
        "clouds": {
          "all": 0
        },
        "wind": {
          "speed": 3.62,
          "deg": 270,
          "gust": 8.69
        },
        "visibility": 10000,
        "pop": 0,
        "sys": {
          "pod": "n"
        },
        "dt_txt": "2026-03-03 15:00:00"
      },
      {
        "dt": 1772560800,
        "main": {
          "temp": 24.21,
          "feels_like": 23.03,
          "temp_min": 24.21,
          "temp_max": 24.21,
          "pressure": 1010,
          "sea_level": 1010,
          "grnd_level": 985,
          "humidity": 13,
          "temp_kf": 0
        },
        "weather": [
          {
            "id": 800,
            "main": "Clear",
            "description": "clear sky",
            "icon": "01n"
          }
        ],
        "clouds": {
          "all": 0
        },
        "wind": {
          "speed": 3.7,
          "deg": 292,
          "gust": 8.58
        },
        "visibility": 10000,
        "pop": 0,
        "sys": {
          "pod": "n"
        },
        "dt_txt": "2026-03-03 18:00:00"
      },
      {
        "dt": 1772571600,
        "main": {
          "temp": 22.18,
          "feels_like": 20.79,
          "temp_min": 22.18,
          "temp_max": 22.18,
          "pressure": 1009,
          "sea_level": 1009,
          "grnd_level": 985,
          "humidity": 13,
          "temp_kf": 0
        },
        "weather": [
          {
            "id": 800,
            "main": "Clear",
            "description": "clear sky",
            "icon": "01n"
          }
        ],
        "clouds": {
          "all": 0
        },
        "wind": {
          "speed": 3.66,
          "deg": 295,
          "gust": 9.33
        },
        "visibility": 10000,
        "pop": 0,
        "sys": {
          "pod": "n"
        },
        "dt_txt": "2026-03-03 21:00:00"
      },
      {
        "dt": 1772582400,
        "main": {
          "temp": 20.89,
          "feels_like": 19.4,
          "temp_min": 20.89,
          "temp_max": 20.89,
          "pressure": 1010,
          "sea_level": 1010,
          "grnd_level": 985,
          "humidity": 14,
          "temp_kf": 0
        },
        "weather": [
          {
            "id": 800,
            "main": "Clear",
            "description": "clear sky",
            "icon": "01n"
          }
        ],
        "clouds": {
          "all": 1
        },
        "wind": {
          "speed": 3.59,
          "deg": 290,
          "gust": 8.82
        },
        "visibility": 10000,
        "pop": 0,
        "sys": {
          "pod": "n"
        },
        "dt_txt": "2026-03-04 00:00:00"
      },
      {
        "dt": 1772593200,
        "main": {
          "temp": 24.14,
          "feels_like": 22.92,
          "temp_min": 24.14,
          "temp_max": 24.14,
          "pressure": 1011,
          "sea_level": 1011,
          "grnd_level": 987,
          "humidity": 12,
          "temp_kf": 0
        },
        "weather": [
          {
            "id": 800,
            "main": "Clear",
            "description": "clear sky",
            "icon": "01d"
          }
        ],
        "clouds": {
          "all": 0
        },
        "wind": {
          "speed": 4.16,
          "deg": 296,
          "gust": 8.3
        },
        "visibility": 10000,
        "pop": 0,
        "sys": {
          "pod": "d"
        },
        "dt_txt": "2026-03-04 03:00:00"
      },
      {
        "dt": 1772604000,
        "main": {
          "temp": 33.47,
          "feels_like": 31.01,
          "temp_min": 33.47,
          "temp_max": 33.47,
          "pressure": 1011,
          "sea_level": 1011,
          "grnd_level": 987,
          "humidity": 8,
          "temp_kf": 0
        },
        "weather": [
          {
            "id": 800,
            "main": "Clear",
            "description": "clear sky",
            "icon": "01d"
          }
        ],
        "clouds": {
          "all": 0
        },
        "wind": {
          "speed": 5.84,
          "deg": 290,
          "gust": 9.66
        },
        "visibility": 10000,
        "pop": 0,
        "sys": {
          "pod": "d"
        },
        "dt_txt": "2026-03-04 06:00:00"
      },
      {
        "dt": 1772614800,
        "main": {
          "temp": 37.35,
          "feels_like": 34.27,
          "temp_min": 37.35,
          "temp_max": 37.35,
          "pressure": 1007,
          "sea_level": 1007,
          "grnd_level": 983,
          "humidity": 7,
          "temp_kf": 0
        },
        "weather": [
          {
            "id": 800,
            "main": "Clear",
            "description": "clear sky",
            "icon": "01d"
          }
        ],
        "clouds": {
          "all": 0
        },
        "wind": {
          "speed": 7.04,
          "deg": 297,
          "gust": 9.26
        },
        "visibility": 10000,
        "pop": 0,
        "sys": {
          "pod": "d"
        },
        "dt_txt": "2026-03-04 09:00:00"
      },
      {
        "dt": 1772625600,
        "main": {
          "temp": 35.7,
          "feels_like": 32.9,
          "temp_min": 35.7,
          "temp_max": 35.7,
          "pressure": 1006,
          "sea_level": 1006,
          "grnd_level": 982,
          "humidity": 8,
          "temp_kf": 0
        },
        "weather": [
          {
            "id": 800,
            "main": "Clear",
            "description": "clear sky",
            "icon": "01d"
          }
        ],
        "clouds": {
          "all": 0
        },
        "wind": {
          "speed": 5.02,
          "deg": 298,
          "gust": 9.01
        },
        "visibility": 10000,
        "pop": 0,
        "sys": {
          "pod": "d"
        },
        "dt_txt": "2026-03-04 12:00:00"
      },
      {
        "dt": 1772636400,
        "main": {
          "temp": 29.64,
          "feels_like": 27.85,
          "temp_min": 29.64,
          "temp_max": 29.64,
          "pressure": 1008,
          "sea_level": 1008,
          "grnd_level": 984,
          "humidity": 14,
          "temp_kf": 0
        },
        "weather": [
          {
            "id": 800,
            "main": "Clear",
            "description": "clear sky",
            "icon": "01n"
          }
        ],
        "clouds": {
          "all": 0
        },
        "wind": {
          "speed": 4.6,
          "deg": 275,
          "gust": 11.26
        },
        "visibility": 10000,
        "pop": 0,
        "sys": {
          "pod": "n"
        },
        "dt_txt": "2026-03-04 15:00:00"
      },
      {
        "dt": 1772647200,
        "main": {
          "temp": 27.48,
          "feels_like": 26.35,
          "temp_min": 27.48,
          "temp_max": 27.48,
          "pressure": 1009,
          "sea_level": 1009,
          "grnd_level": 985,
          "humidity": 18,
          "temp_kf": 0
        },
        "weather": [
          {
            "id": 800,
            "main": "Clear",
            "description": "clear sky",
            "icon": "01n"
          }
        ],
        "clouds": {
          "all": 0
        },
        "wind": {
          "speed": 4.83,
          "deg": 294,
          "gust": 12.96
        },
        "visibility": 10000,
        "pop": 0,
        "sys": {
          "pod": "n"
        },
        "dt_txt": "2026-03-04 18:00:00"
      },
      {
        "dt": 1772658000,
        "main": {
          "temp": 25.14,
          "feels_like": 24.21,
          "temp_min": 25.14,
          "temp_max": 25.14,
          "pressure": 1008,
          "sea_level": 1008,
          "grnd_level": 983,
          "humidity": 19,
          "temp_kf": 0
        },
        "weather": [
          {
            "id": 800,
            "main": "Clear",
            "description": "clear sky",
            "icon": "01n"
          }
        ],
        "clouds": {
          "all": 0
        },
        "wind": {
          "speed": 4.61,
          "deg": 293,
          "gust": 12.85
        },
        "visibility": 10000,
        "pop": 0,
        "sys": {
          "pod": "n"
        },
        "dt_txt": "2026-03-04 21:00:00"
      }
    ],
    "city": {
      "id": 1271308,
      "name": "Ghaziabad",
      "coord": {
        "lat": 28.6692,
        "lon": 77.438
      },
      "country": "IN",
      "population": 1199191,
      "timezone": 19800,
      "sunrise": 1772241420,
      "sunset": 1772282944
    }
  },
  "tomorrow": {
    "data": {
      "time": "2026-02-27T22:56:00Z",
      "values": {
        "altimeterSetting": 1006.91,
        "cloudBase": 3.8,
        "cloudCeiling": null,
        "cloudCover": 36,
        "dewPoint": 12.5,
        "freezingRainIntensity": 0,
        "humidity": 85,
        "precipitationProbability": 0,
        "pressureSeaLevel": 1006.51,
        "pressureSurfaceLevel": 982.57,
        "rainIntensity": 0,
        "sleetIntensity": 0,
        "snowIntensity": 0,
        "temperature": 15.1,
        "temperatureApparent": 15.1,
        "uvHealthConcern": 0,
        "uvIndex": 0,
        "visibility": 16,
        "weatherCode": 1100,
        "windDirection": 10,
        "windGust": 1,
        "windSpeed": 0.4
      }
    },
    "location": {
      "lat": 28.6692,
      "lon": 77.438
    }
  }
}